[
  {
    "signature": "async ExtractEventFromLogs({\n  \"abi\": [\n    {\n      \"constant\": true,\n      \"inputs\": [],\n      \"name\": \"STATUS_PUBLISHED\",\n      \"outputs\": [\n        {\n          \"name\": \"\",\n          \"type\": \"bytes32\"\n        }\n      ],\n      \"payable\": false,\n      \"stateMutability\": \"view\",\n      \"type\": \"function\"\n    },\n    {\n      \"constant\": true,\n      \"inputs\": [],\n      \"name\": \"creator\",\n      \"outputs\": [\n        {\n          \"name\": \"\",\n          \"type\": \"address\"\n        }\n      ],\n      \"payable\": false,\n      \"stateMutability\": \"view\",\n      \"type\": \"function\"\n    },\n    {\n      \"constant\": false,\n      \"inputs\": [],\n      \"name\": \"publish\",\n      \"outputs\": [\n        {\n          \"name\": \"\",\n          \"type\": \"bool\"\n        }\n      ],\n      \"payable\": true,\n      \"stateMutability\": \"payable\",\n      \"type\": \"function\"\n    },\n    {\n      \"constant\": false,\n      \"inputs\": [\n        {\n          \"name\": \"request_ID\",\n          \"type\": \"uint256\"\n        },\n        {\n          \"name\": \"payee\",\n          \"type\": \"address\"\n        },\n        {\n          \"name\": \"label\",\n          \"type\": \"string\"\n        },\n        {\n          \"name\": \"amount\",\n          \"type\": \"uint256\"\n        }\n      ],\n      \"name\": \"processRequestPayment\",\n      \"outputs\": [\n        {\n          \"name\": \"\",\n          \"type\": \"bool\"\n        }\n      ],\n      \"payable\": false,\n      \"stateMutability\": \"nonpayable\",\n      \"type\": \"function\"\n    },\n    {\n      \"constant\": true,\n      \"inputs\": [\n        {\n          \"name\": \"\",\n          \"type\": \"uint256\"\n        }\n      ],\n      \"name\": \"requestMap\",\n      \"outputs\": [\n        {\n          \"name\": \"originator\",\n          \"type\": \"address\"\n        },\n        {\n          \"name\": \"amountPaid\",\n          \"type\": \"uint256\"\n        },\n        {\n          \"name\": \"status\",\n          \"type\": \"int8\"\n        },\n        {\n          \"name\": \"settled\",\n          \"type\": \"uint256\"\n        }\n      ],\n      \"payable\": false,\n      \"stateMutability\": \"view\",\n      \"type\": \"function\"\n    },\n    {\n      \"constant\": true,\n      \"inputs\": [],\n      \"name\": \"contentContractAddress\",\n      \"outputs\": [\n        {\n          \"name\": \"\",\n          \"type\": \"address\"\n        }\n      ],\n      \"payable\": false,\n      \"stateMutability\": \"view\",\n      \"type\": \"function\"\n    },\n    {\n      \"constant\": true,\n      \"inputs\": [],\n      \"name\": \"statusCode\",\n      \"outputs\": [\n        {\n          \"name\": \"\",\n          \"type\": \"int256\"\n        }\n      ],\n      \"payable\": false,\n      \"stateMutability\": \"view\",\n      \"type\": \"function\"\n    },\n    {\n      \"constant\": true,\n      \"inputs\": [],\n      \"name\": \"addressKMS\",\n      \"outputs\": [\n        {\n          \"name\": \"\",\n          \"type\": \"address\"\n        }\n      ],\n      \"payable\": false,\n      \"stateMutability\": \"view\",\n      \"type\": \"function\"\n    },\n    {\n      \"constant\": true,\n      \"inputs\": [],\n      \"name\": \"contentType\",\n      \"outputs\": [\n        {\n          \"name\": \"\",\n          \"type\": \"address\"\n        }\n      ],\n      \"payable\": false,\n      \"stateMutability\": \"view\",\n      \"type\": \"function\"\n    },\n    {\n      \"constant\": true,\n      \"inputs\": [\n        {\n          \"name\": \"status_code\",\n          \"type\": \"int256\"\n        }\n      ],\n      \"name\": \"statusCodeDescription\",\n      \"outputs\": [\n        {\n          \"name\": \"\",\n          \"type\": \"bytes32\"\n        }\n      ],\n      \"payable\": false,\n      \"stateMutability\": \"view\",\n      \"type\": \"function\"\n    },\n    {\n      \"constant\": true,\n      \"inputs\": [\n        {\n          \"name\": \"level\",\n          \"type\": \"uint8\"\n        },\n        {\n          \"name\": \"custom_values\",\n          \"type\": \"bytes32[]\"\n        },\n        {\n          \"name\": \"stakeholders\",\n          \"type\": \"address[]\"\n        }\n      ],\n      \"name\": \"getAccessInfo\",\n      \"outputs\": [\n        {\n          \"name\": \"\",\n          \"type\": \"int8\"\n        },\n        {\n          \"name\": \"\",\n          \"type\": \"uint256\"\n        }\n      ],\n      \"payable\": false,\n      \"stateMutability\": \"view\",\n      \"type\": \"function\"\n    },\n    {\n      \"constant\": false,\n      \"inputs\": [],\n      \"name\": \"kill\",\n      \"outputs\": [],\n      \"payable\": false,\n      \"stateMutability\": \"nonpayable\",\n      \"type\": \"function\"\n    },\n    {\n      \"constant\": true,\n      \"inputs\": [],\n      \"name\": \"STATUS_DRAFT\",\n      \"outputs\": [\n        {\n          \"name\": \"\",\n          \"type\": \"bytes32\"\n        }\n      ],\n      \"payable\": false,\n      \"stateMutability\": \"view\",\n      \"type\": \"function\"\n    },\n    {\n      \"constant\": false,\n      \"inputs\": [\n        {\n          \"name\": \"status_code\",\n          \"type\": \"int256\"\n        }\n      ],\n      \"name\": \"setStatusCode\",\n      \"outputs\": [\n        {\n          \"name\": \"\",\n          \"type\": \"int256\"\n        }\n      ],\n      \"payable\": false,\n      \"stateMutability\": \"nonpayable\",\n      \"type\": \"function\"\n    },\n    {\n      \"constant\": true,\n      \"inputs\": [],\n      \"name\": \"version\",\n      \"outputs\": [\n        {\n          \"name\": \"\",\n          \"type\": \"bytes32\"\n        }\n      ],\n      \"payable\": false,\n      \"stateMutability\": \"view\",\n      \"type\": \"function\"\n    },\n    {\n      \"constant\": false,\n      \"inputs\": [\n        {\n          \"name\": \"request_ID\",\n          \"type\": \"uint256\"\n        },\n        {\n          \"name\": \"score_pct\",\n          \"type\": \"uint256\"\n        },\n        {\n          \"name\": \"ml_out_hash\",\n          \"type\": \"bytes32\"\n        }\n      ],\n      \"name\": \"accessComplete\",\n      \"outputs\": [\n        {\n          \"name\": \"\",\n          \"type\": \"bool\"\n        }\n      ],\n      \"payable\": true,\n      \"stateMutability\": \"payable\",\n      \"type\": \"function\"\n    },\n    {\n      \"constant\": true,\n      \"inputs\": [],\n      \"name\": \"accessCharge\",\n      \"outputs\": [\n        {\n          \"name\": \"\",\n          \"type\": \"uint256\"\n        }\n      ],\n      \"payable\": false,\n      \"stateMutability\": \"view\",\n      \"type\": \"function\"\n    },\n    {\n      \"constant\": false,\n      \"inputs\": [\n        {\n          \"name\": \"newCreator\",\n          \"type\": \"address\"\n        }\n      ],\n      \"name\": \"transferCreatorship\",\n      \"outputs\": [],\n      \"payable\": false,\n      \"stateMutability\": \"nonpayable\",\n      \"type\": \"function\"\n    },\n    {\n      \"constant\": true,\n      \"inputs\": [\n        {\n          \"name\": \"\",\n          \"type\": \"uint256\"\n        }\n      ],\n      \"name\": \"versionHashes\",\n      \"outputs\": [\n        {\n          \"name\": \"\",\n          \"type\": \"bytes32\"\n        }\n      ],\n      \"payable\": false,\n      \"stateMutability\": \"view\",\n      \"type\": \"function\"\n    },\n    {\n      \"constant\": false,\n      \"inputs\": [\n        {\n          \"name\": \"status_code\",\n          \"type\": \"int256\"\n        }\n      ],\n      \"name\": \"updateStatus\",\n      \"outputs\": [\n        {\n          \"name\": \"\",\n          \"type\": \"int256\"\n        }\n      ],\n      \"payable\": false,\n      \"stateMutability\": \"nonpayable\",\n      \"type\": \"function\"\n    },\n    {\n      \"constant\": false,\n      \"inputs\": [\n        {\n          \"name\": \"level\",\n          \"type\": \"uint8\"\n        },\n        {\n          \"name\": \"custom_values\",\n          \"type\": \"bytes32[]\"\n        },\n        {\n          \"name\": \"stakeholders\",\n          \"type\": \"address[]\"\n        }\n      ],\n      \"name\": \"getAccessCharge\",\n      \"outputs\": [\n        {\n          \"name\": \"\",\n          \"type\": \"uint256\"\n        }\n      ],\n      \"payable\": false,\n      \"stateMutability\": \"nonpayable\",\n      \"type\": \"function\"\n    },\n    {\n      \"constant\": true,\n      \"inputs\": [],\n      \"name\": \"owner\",\n      \"outputs\": [\n        {\n          \"name\": \"\",\n          \"type\": \"address\"\n        }\n      ],\n      \"payable\": false,\n      \"stateMutability\": \"view\",\n      \"type\": \"function\"\n    },\n    {\n      \"constant\": true,\n      \"inputs\": [],\n      \"name\": \"requestID\",\n      \"outputs\": [\n        {\n          \"name\": \"\",\n          \"type\": \"uint256\"\n        }\n      ],\n      \"payable\": false,\n      \"stateMutability\": \"view\",\n      \"type\": \"function\"\n    },\n    {\n      \"constant\": false,\n      \"inputs\": [\n        {\n          \"name\": \"level\",\n          \"type\": \"uint8\"\n        },\n        {\n          \"name\": \"pke_requestor\",\n          \"type\": \"string\"\n        },\n        {\n          \"name\": \"pke_AFGH\",\n          \"type\": \"string\"\n        },\n        {\n          \"name\": \"custom_values\",\n          \"type\": \"bytes32[]\"\n        },\n        {\n          \"name\": \"stakeholders\",\n          \"type\": \"address[]\"\n        }\n      ],\n      \"name\": \"accessRequest\",\n      \"outputs\": [\n        {\n          \"name\": \"\",\n          \"type\": \"bool\"\n        }\n      ],\n      \"payable\": true,\n      \"stateMutability\": \"payable\",\n      \"type\": \"function\"\n    },\n    {\n      \"constant\": true,\n      \"inputs\": [],\n      \"name\": \"libraryAddress\",\n      \"outputs\": [\n        {\n          \"name\": \"\",\n          \"type\": \"address\"\n        }\n      ],\n      \"payable\": false,\n      \"stateMutability\": \"view\",\n      \"type\": \"function\"\n    },\n    {\n      \"constant\": false,\n      \"inputs\": [],\n      \"name\": \"updateRequest\",\n      \"outputs\": [],\n      \"payable\": false,\n      \"stateMutability\": \"nonpayable\",\n      \"type\": \"function\"\n    },\n    {\n      \"constant\": false,\n      \"inputs\": [\n        {\n          \"name\": \"address_KMS\",\n          \"type\": \"address\"\n        }\n      ],\n      \"name\": \"setAddressKMS\",\n      \"outputs\": [],\n      \"payable\": false,\n      \"stateMutability\": \"nonpayable\",\n      \"type\": \"function\"\n    },\n    {\n      \"constant\": true,\n      \"inputs\": [],\n      \"name\": \"canPublish\",\n      \"outputs\": [\n        {\n          \"name\": \"\",\n          \"type\": \"bool\"\n        }\n      ],\n      \"payable\": false,\n      \"stateMutability\": \"view\",\n      \"type\": \"function\"\n    },\n    {\n      \"constant\": true,\n      \"inputs\": [],\n      \"name\": \"STATUS_REVIEW\",\n      \"outputs\": [\n        {\n          \"name\": \"\",\n          \"type\": \"bytes32\"\n        }\n      ],\n      \"payable\": false,\n      \"stateMutability\": \"view\",\n      \"type\": \"function\"\n    },\n    {\n      \"constant\": true,\n      \"inputs\": [],\n      \"name\": \"objectHash\",\n      \"outputs\": [\n        {\n          \"name\": \"\",\n          \"type\": \"bytes32\"\n        }\n      ],\n      \"payable\": false,\n      \"stateMutability\": \"view\",\n      \"type\": \"function\"\n    },\n    {\n      \"constant\": false,\n      \"inputs\": [\n        {\n          \"name\": \"addr\",\n          \"type\": \"address\"\n        }\n      ],\n      \"name\": \"setContentContractAddress\",\n      \"outputs\": [],\n      \"payable\": false,\n      \"stateMutability\": \"nonpayable\",\n      \"type\": \"function\"\n    },\n    {\n      \"constant\": false,\n      \"inputs\": [\n        {\n          \"name\": \"request_ID\",\n          \"type\": \"uint256\"\n        },\n        {\n          \"name\": \"access_granted\",\n          \"type\": \"bool\"\n        },\n        {\n          \"name\": \"re_key\",\n          \"type\": \"string\"\n        },\n        {\n          \"name\": \"encrypted_AES_key\",\n          \"type\": \"string\"\n        }\n      ],\n      \"name\": \"accessGrant\",\n      \"outputs\": [\n        {\n          \"name\": \"\",\n          \"type\": \"bool\"\n        }\n      ],\n      \"payable\": false,\n      \"stateMutability\": \"nonpayable\",\n      \"type\": \"function\"\n    },\n    {\n      \"constant\": false,\n      \"inputs\": [\n        {\n          \"name\": \"_objectHash\",\n          \"type\": \"bytes32\"\n        }\n      ],\n      \"name\": \"commit\",\n      \"outputs\": [],\n      \"payable\": false,\n      \"stateMutability\": \"nonpayable\",\n      \"type\": \"function\"\n    },\n    {\n      \"constant\": false,\n      \"inputs\": [\n        {\n          \"name\": \"newOwner\",\n          \"type\": \"address\"\n        }\n      ],\n      \"name\": \"transferOwnership\",\n      \"outputs\": [],\n      \"payable\": false,\n      \"stateMutability\": \"nonpayable\",\n      \"type\": \"function\"\n    },\n    {\n      \"constant\": false,\n      \"inputs\": [\n        {\n          \"name\": \"charge\",\n          \"type\": \"uint256\"\n        }\n      ],\n      \"name\": \"setAccessCharge\",\n      \"outputs\": [\n        {\n          \"name\": \"\",\n          \"type\": \"uint256\"\n        }\n      ],\n      \"payable\": false,\n      \"stateMutability\": \"nonpayable\",\n      \"type\": \"function\"\n    },\n    {\n      \"constant\": true,\n      \"inputs\": [],\n      \"name\": \"statusDescription\",\n      \"outputs\": [\n        {\n          \"name\": \"\",\n          \"type\": \"bytes32\"\n        }\n      ],\n      \"payable\": false,\n      \"stateMutability\": \"view\",\n      \"type\": \"function\"\n    },\n    {\n      \"inputs\": [\n        {\n          \"name\": \"content_type\",\n          \"type\": \"address\"\n        }\n      ],\n      \"payable\": true,\n      \"stateMutability\": \"payable\",\n      \"type\": \"constructor\"\n    },\n    {\n      \"payable\": true,\n      \"stateMutability\": \"payable\",\n      \"type\": \"fallback\"\n    },\n    {\n      \"anonymous\": false,\n      \"inputs\": [\n        {\n          \"indexed\": false,\n          \"name\": \"containingLibrary\",\n          \"type\": \"address\"\n        }\n      ],\n      \"name\": \"ContentObjectCreate\",\n      \"type\": \"event\"\n    },\n    {\n      \"anonymous\": false,\n      \"inputs\": [\n        {\n          \"indexed\": false,\n          \"name\": \"contentType\",\n          \"type\": \"address\"\n        },\n        {\n          \"indexed\": false,\n          \"name\": \"contentContractAddress\",\n          \"type\": \"address\"\n        }\n      ],\n      \"name\": \"SetContentType\",\n      \"type\": \"event\"\n    },\n    {\n      \"anonymous\": false,\n      \"inputs\": [\n        {\n          \"indexed\": false,\n          \"name\": \"requestID\",\n          \"type\": \"uint256\"\n        },\n        {\n          \"indexed\": false,\n          \"name\": \"level\",\n          \"type\": \"uint8\"\n        },\n        {\n          \"indexed\": false,\n          \"name\": \"contentHash\",\n          \"type\": \"bytes32\"\n        },\n        {\n          \"indexed\": false,\n          \"name\": \"pkeRequestor\",\n          \"type\": \"string\"\n        },\n        {\n          \"indexed\": false,\n          \"name\": \"pkeAFGH\",\n          \"type\": \"string\"\n        }\n      ],\n      \"name\": \"AccessRequest\",\n      \"type\": \"event\"\n    },\n    {\n      \"anonymous\": false,\n      \"inputs\": [\n        {\n          \"indexed\": false,\n          \"name\": \"requestID\",\n          \"type\": \"uint256\"\n        },\n        {\n          \"indexed\": false,\n          \"name\": \"label\",\n          \"type\": \"string\"\n        },\n        {\n          \"indexed\": false,\n          \"name\": \"payee\",\n          \"type\": \"address\"\n        },\n        {\n          \"indexed\": false,\n          \"name\": \"amount\",\n          \"type\": \"uint256\"\n        }\n      ],\n      \"name\": \"LogPayment\",\n      \"type\": \"event\"\n    },\n    {\n      \"anonymous\": false,\n      \"inputs\": [\n        {\n          \"indexed\": false,\n          \"name\": \"requestID\",\n          \"type\": \"uint256\"\n        },\n        {\n          \"indexed\": false,\n          \"name\": \"access_granted\",\n          \"type\": \"bool\"\n        },\n        {\n          \"indexed\": false,\n          \"name\": \"reKey\",\n          \"type\": \"string\"\n        },\n        {\n          \"indexed\": false,\n          \"name\": \"encryptedAESKey\",\n          \"type\": \"string\"\n        }\n      ],\n      \"name\": \"AccessGrant\",\n      \"type\": \"event\"\n    },\n    {\n      \"anonymous\": false,\n      \"inputs\": [\n        {\n          \"indexed\": false,\n          \"name\": \"customValue\",\n          \"type\": \"bytes32\"\n        }\n      ],\n      \"name\": \"AccessRequestValue\",\n      \"type\": \"event\"\n    },\n    {\n      \"anonymous\": false,\n      \"inputs\": [\n        {\n          \"indexed\": false,\n          \"name\": \"stakeholder\",\n          \"type\": \"address\"\n        }\n      ],\n      \"name\": \"AccessRequestStakeholder\",\n      \"type\": \"event\"\n    },\n    {\n      \"anonymous\": false,\n      \"inputs\": [\n        {\n          \"indexed\": false,\n          \"name\": \"requestID\",\n          \"type\": \"uint256\"\n        },\n        {\n          \"indexed\": false,\n          \"name\": \"scorePct\",\n          \"type\": \"uint256\"\n        },\n        {\n          \"indexed\": false,\n          \"name\": \"mlOutHash\",\n          \"type\": \"bytes32\"\n        },\n        {\n          \"indexed\": false,\n          \"name\": \"customContractResult\",\n          \"type\": \"bool\"\n        }\n      ],\n      \"name\": \"AccessComplete\",\n      \"type\": \"event\"\n    },\n    {\n      \"anonymous\": false,\n      \"inputs\": [\n        {\n          \"indexed\": false,\n          \"name\": \"contentContractAddress\",\n          \"type\": \"address\"\n        }\n      ],\n      \"name\": \"SetContentContract\",\n      \"type\": \"event\"\n    },\n    {\n      \"anonymous\": false,\n      \"inputs\": [\n        {\n          \"indexed\": false,\n          \"name\": \"accessCharge\",\n          \"type\": \"uint256\"\n        }\n      ],\n      \"name\": \"SetAccessCharge\",\n      \"type\": \"event\"\n    },\n    {\n      \"anonymous\": false,\n      \"inputs\": [\n        {\n          \"indexed\": false,\n          \"name\": \"level\",\n          \"type\": \"uint8\"\n        },\n        {\n          \"indexed\": false,\n          \"name\": \"accessCharge\",\n          \"type\": \"uint256\"\n        }\n      ],\n      \"name\": \"GetAccessCharge\",\n      \"type\": \"event\"\n    },\n    {\n      \"anonymous\": false,\n      \"inputs\": [\n        {\n          \"indexed\": false,\n          \"name\": \"accessCharge\",\n          \"type\": \"uint256\"\n        },\n        {\n          \"indexed\": false,\n          \"name\": \"amountProvided\",\n          \"type\": \"uint256\"\n        }\n      ],\n      \"name\": \"InsufficientFunds\",\n      \"type\": \"event\"\n    },\n    {\n      \"anonymous\": false,\n      \"inputs\": [\n        {\n          \"indexed\": false,\n          \"name\": \"statusCode\",\n          \"type\": \"int256\"\n        }\n      ],\n      \"name\": \"SetStatusCode\",\n      \"type\": \"event\"\n    },\n    {\n      \"anonymous\": false,\n      \"inputs\": [\n        {\n          \"indexed\": false,\n          \"name\": \"requestStatus\",\n          \"type\": \"bool\"\n        },\n        {\n          \"indexed\": false,\n          \"name\": \"statusCode\",\n          \"type\": \"int256\"\n        },\n        {\n          \"indexed\": false,\n          \"name\": \"objectHash\",\n          \"type\": \"bytes32\"\n        }\n      ],\n      \"name\": \"Publish\",\n      \"type\": \"event\"\n    },\n    {\n      \"anonymous\": false,\n      \"inputs\": [\n        {\n          \"indexed\": false,\n          \"name\": \"custom_contract\",\n          \"type\": \"address\"\n        }\n      ],\n      \"name\": \"InvokeCustomPreHook\",\n      \"type\": \"event\"\n    },\n    {\n      \"anonymous\": false,\n      \"inputs\": [\n        {\n          \"indexed\": false,\n          \"name\": \"custom_contract\",\n          \"type\": \"address\"\n        },\n        {\n          \"indexed\": false,\n          \"name\": \"result\",\n          \"type\": \"uint256\"\n        }\n      ],\n      \"name\": \"ReturnCustomHook\",\n      \"type\": \"event\"\n    },\n    {\n      \"anonymous\": false,\n      \"inputs\": [\n        {\n          \"indexed\": false,\n          \"name\": \"custom_contract\",\n          \"type\": \"address\"\n        }\n      ],\n      \"name\": \"InvokeCustomPostHook\",\n      \"type\": \"event\"\n    },\n    {\n      \"anonymous\": false,\n      \"inputs\": [\n        {\n          \"indexed\": false,\n          \"name\": \"objectHash\",\n          \"type\": \"bytes32\"\n        }\n      ],\n      \"name\": \"CommitPending\",\n      \"type\": \"event\"\n    },\n    {\n      \"anonymous\": false,\n      \"inputs\": [\n        {\n          \"indexed\": false,\n          \"name\": \"objectHash\",\n          \"type\": \"bytes32\"\n        }\n      ],\n      \"name\": \"Commit\",\n      \"type\": \"event\"\n    },\n    {\n      \"anonymous\": false,\n      \"inputs\": [\n        {\n          \"indexed\": false,\n          \"name\": \"objectHash\",\n          \"type\": \"bytes32\"\n        }\n      ],\n      \"name\": \"UpdateRequest\",\n      \"type\": \"event\"\n    }\n  ],\n  \"event\": {\n    \"to\": \"0x61E76Bc8b01352A2b12d8e8949F9c1CDF6ca447D\",\n    \"from\": \"0xc2635Ab30Fc19F616332c6d2d7F14cdAf7ce1965\",\n    \"contractAddress\": null,\n    \"transactionIndex\": 0,\n    \"gasUsed\": {\n      \"_hex\": \"0x181c3\"\n    },\n    \"logsBloom\": \"0x00000000000000000000000000040000000000000000000000000000000000000000000000000000000000000000000000000000000000000000000000000000080000000000000004000000000000000000000000000000000000000000000000400000000000000000000000000000000000000000000000000000000000000000000000000000000000000000000000000000000000000001000000000000000000000000000000000000000000000000000000000000000000000000000000000000000000000000000000000000000000000000000000000000000000000000000000000000000000000000000000000000000000000000002000000000\",\n    \"blockHash\": \"0x8915b6dcf3d39bf7e909be8f256bb4927f28939dedbab92b2aaea5721024a8e0\",\n    \"transactionHash\": \"0xfe6bce66d643749c28505516a3b022c7cea4ef25ca98935257babb90b1db4c1b\",\n    \"logs\": [\n      {\n        \"transactionIndex\": 0,\n        \"blockNumber\": 744,\n        \"transactionHash\": \"0xfe6bce66d643749c28505516a3b022c7cea4ef25ca98935257babb90b1db4c1b\",\n        \"address\": \"0x61E76Bc8b01352A2b12d8e8949F9c1CDF6ca447D\",\n        \"topics\": [\n          \"0x089a6f1788a3c353423e1be4ba12533bdde7d908bb41abeee185af0acb3df562\"\n        ],\n        \"data\": \"0x00000000000000000000000000000000000000000000000000000000000000010000000000000000000000000000000000000000000000000000000000000000000000000000000000000000000000000000000000000000000000000000000000000000000000000000000000000000000000000000000000000000000000a000000000000000000000000000000000000000000000000000000000000001600000000000000000000000000000000000000000000000000000000000000084307830346662626561336262633038303466303565383233643233313232383538666137323164663765396331363939336238316362373761323961373236393361303733626562633030383730343737323036626531623830383037306162316162666231366365616264613963623535643633623332653734396230623162633033000000000000000000000000000000000000000000000000000000000000000000000000000000000000000000000000000000000000000000000000\",\n        \"logIndex\": 0,\n        \"blockHash\": \"0x8915b6dcf3d39bf7e909be8f256bb4927f28939dedbab92b2aaea5721024a8e0\",\n        \"transactionLogIndex\": 0,\n        \"name\": \"AccessRequest\",\n        \"signature\": \"AccessRequest(uint256,uint8,bytes32,string,string)\",\n        \"topic\": \"0x089a6f1788a3c353423e1be4ba12533bdde7d908bb41abeee185af0acb3df562\",\n        \"values\": {\n          \"0\": {\n            \"_hex\": \"0x01\"\n          },\n          \"1\": 0,\n          \"2\": \"0x0000000000000000000000000000000000000000000000000000000000000000\",\n          \"3\": \"0x04fbbea3bbc0804f05e823d23122858fa721df7e9c16993b81cb77a29a72693a073bebc00870477206be1b808070ab1abfb16ceabda9cb55d63b32e749b0b1bc03\",\n          \"4\": \"\",\n          \"requestID\": {\n            \"_hex\": \"0x01\"\n          },\n          \"level\": 0,\n          \"contentHash\": \"0x0000000000000000000000000000000000000000000000000000000000000000\",\n          \"pkeRequestor\": \"0x04fbbea3bbc0804f05e823d23122858fa721df7e9c16993b81cb77a29a72693a073bebc00870477206be1b808070ab1abfb16ceabda9cb55d63b32e749b0b1bc03\",\n          \"pkeAFGH\": \"\",\n          \"length\": 5\n        }\n      }\n    ],\n    \"blockNumber\": 744,\n    \"confirmations\": 2,\n    \"cumulativeGasUsed\": {\n      \"_hex\": \"0x181c3\"\n    },\n    \"status\": 1,\n    \"byzantium\": true\n  },\n  \"eventName\": \"AccessRequest\"\n});",
    "result": "{\n  \"name\": \"AccessRequest\",\n  \"signature\": \"AccessRequest(uint256,uint8,bytes32,string,string)\",\n  \"topic\": \"0x089a6f1788a3c353423e1be4ba12533bdde7d908bb41abeee185af0acb3df562\",\n  \"values\": {\n    \"0\": {\n      \"_hex\": \"0x01\"\n    },\n    \"1\": 0,\n    \"2\": \"0x0000000000000000000000000000000000000000000000000000000000000000\",\n    \"3\": \"0x04fbbea3bbc0804f05e823d23122858fa721df7e9c16993b81cb77a29a72693a073bebc00870477206be1b808070ab1abfb16ceabda9cb55d63b32e749b0b1bc03\",\n    \"4\": \"\",\n    \"requestID\": {\n      \"_hex\": \"0x01\"\n    },\n    \"level\": 0,\n    \"contentHash\": \"0x0000000000000000000000000000000000000000000000000000000000000000\",\n    \"pkeRequestor\": \"0x04fbbea3bbc0804f05e823d23122858fa721df7e9c16993b81cb77a29a72693a073bebc00870477206be1b808070ab1abfb16ceabda9cb55d63b32e749b0b1bc03\",\n    \"pkeAFGH\": \"\",\n    \"length\": 5\n  }\n}"
  },
  {
    "signature": "async ExtractEventFromLogs({\n  \"abi\": [\n    {\n      \"constant\": true,\n      \"inputs\": [],\n      \"name\": \"STATUS_PUBLISHED\",\n      \"outputs\": [\n        {\n          \"name\": \"\",\n          \"type\": \"bytes32\"\n        }\n      ],\n      \"payable\": false,\n      \"stateMutability\": \"view\",\n      \"type\": \"function\"\n    },\n    {\n      \"constant\": true,\n      \"inputs\": [],\n      \"name\": \"creator\",\n      \"outputs\": [\n        {\n          \"name\": \"\",\n          \"type\": \"address\"\n        }\n      ],\n      \"payable\": false,\n      \"stateMutability\": \"view\",\n      \"type\": \"function\"\n    },\n    {\n      \"constant\": false,\n      \"inputs\": [],\n      \"name\": \"publish\",\n      \"outputs\": [\n        {\n          \"name\": \"\",\n          \"type\": \"bool\"\n        }\n      ],\n      \"payable\": true,\n      \"stateMutability\": \"payable\",\n      \"type\": \"function\"\n    },\n    {\n      \"constant\": false,\n      \"inputs\": [\n        {\n          \"name\": \"request_ID\",\n          \"type\": \"uint256\"\n        },\n        {\n          \"name\": \"payee\",\n          \"type\": \"address\"\n        },\n        {\n          \"name\": \"label\",\n          \"type\": \"string\"\n        },\n        {\n          \"name\": \"amount\",\n          \"type\": \"uint256\"\n        }\n      ],\n      \"name\": \"processRequestPayment\",\n      \"outputs\": [\n        {\n          \"name\": \"\",\n          \"type\": \"bool\"\n        }\n      ],\n      \"payable\": false,\n      \"stateMutability\": \"nonpayable\",\n      \"type\": \"function\"\n    },\n    {\n      \"constant\": true,\n      \"inputs\": [\n        {\n          \"name\": \"\",\n          \"type\": \"uint256\"\n        }\n      ],\n      \"name\": \"requestMap\",\n      \"outputs\": [\n        {\n          \"name\": \"originator\",\n          \"type\": \"address\"\n        },\n        {\n          \"name\": \"amountPaid\",\n          \"type\": \"uint256\"\n        },\n        {\n          \"name\": \"status\",\n          \"type\": \"int8\"\n        },\n        {\n          \"name\": \"settled\",\n          \"type\": \"uint256\"\n        }\n      ],\n      \"payable\": false,\n      \"stateMutability\": \"view\",\n      \"type\": \"function\"\n    },\n    {\n      \"constant\": true,\n      \"inputs\": [],\n      \"name\": \"contentContractAddress\",\n      \"outputs\": [\n        {\n          \"name\": \"\",\n          \"type\": \"address\"\n        }\n      ],\n      \"payable\": false,\n      \"stateMutability\": \"view\",\n      \"type\": \"function\"\n    },\n    {\n      \"constant\": true,\n      \"inputs\": [],\n      \"name\": \"statusCode\",\n      \"outputs\": [\n        {\n          \"name\": \"\",\n          \"type\": \"int256\"\n        }\n      ],\n      \"payable\": false,\n      \"stateMutability\": \"view\",\n      \"type\": \"function\"\n    },\n    {\n      \"constant\": true,\n      \"inputs\": [],\n      \"name\": \"addressKMS\",\n      \"outputs\": [\n        {\n          \"name\": \"\",\n          \"type\": \"address\"\n        }\n      ],\n      \"payable\": false,\n      \"stateMutability\": \"view\",\n      \"type\": \"function\"\n    },\n    {\n      \"constant\": true,\n      \"inputs\": [],\n      \"name\": \"contentType\",\n      \"outputs\": [\n        {\n          \"name\": \"\",\n          \"type\": \"address\"\n        }\n      ],\n      \"payable\": false,\n      \"stateMutability\": \"view\",\n      \"type\": \"function\"\n    },\n    {\n      \"constant\": true,\n      \"inputs\": [\n        {\n          \"name\": \"status_code\",\n          \"type\": \"int256\"\n        }\n      ],\n      \"name\": \"statusCodeDescription\",\n      \"outputs\": [\n        {\n          \"name\": \"\",\n          \"type\": \"bytes32\"\n        }\n      ],\n      \"payable\": false,\n      \"stateMutability\": \"view\",\n      \"type\": \"function\"\n    },\n    {\n      \"constant\": true,\n      \"inputs\": [\n        {\n          \"name\": \"level\",\n          \"type\": \"uint8\"\n        },\n        {\n          \"name\": \"custom_values\",\n          \"type\": \"bytes32[]\"\n        },\n        {\n          \"name\": \"stakeholders\",\n          \"type\": \"address[]\"\n        }\n      ],\n      \"name\": \"getAccessInfo\",\n      \"outputs\": [\n        {\n          \"name\": \"\",\n          \"type\": \"int8\"\n        },\n        {\n          \"name\": \"\",\n          \"type\": \"uint256\"\n        }\n      ],\n      \"payable\": false,\n      \"stateMutability\": \"view\",\n      \"type\": \"function\"\n    },\n    {\n      \"constant\": false,\n      \"inputs\": [],\n      \"name\": \"kill\",\n      \"outputs\": [],\n      \"payable\": false,\n      \"stateMutability\": \"nonpayable\",\n      \"type\": \"function\"\n    },\n    {\n      \"constant\": true,\n      \"inputs\": [],\n      \"name\": \"STATUS_DRAFT\",\n      \"outputs\": [\n        {\n          \"name\": \"\",\n          \"type\": \"bytes32\"\n        }\n      ],\n      \"payable\": false,\n      \"stateMutability\": \"view\",\n      \"type\": \"function\"\n    },\n    {\n      \"constant\": false,\n      \"inputs\": [\n        {\n          \"name\": \"status_code\",\n          \"type\": \"int256\"\n        }\n      ],\n      \"name\": \"setStatusCode\",\n      \"outputs\": [\n        {\n          \"name\": \"\",\n          \"type\": \"int256\"\n        }\n      ],\n      \"payable\": false,\n      \"stateMutability\": \"nonpayable\",\n      \"type\": \"function\"\n    },\n    {\n      \"constant\": true,\n      \"inputs\": [],\n      \"name\": \"version\",\n      \"outputs\": [\n        {\n          \"name\": \"\",\n          \"type\": \"bytes32\"\n        }\n      ],\n      \"payable\": false,\n      \"stateMutability\": \"view\",\n      \"type\": \"function\"\n    },\n    {\n      \"constant\": false,\n      \"inputs\": [\n        {\n          \"name\": \"request_ID\",\n          \"type\": \"uint256\"\n        },\n        {\n          \"name\": \"score_pct\",\n          \"type\": \"uint256\"\n        },\n        {\n          \"name\": \"ml_out_hash\",\n          \"type\": \"bytes32\"\n        }\n      ],\n      \"name\": \"accessComplete\",\n      \"outputs\": [\n        {\n          \"name\": \"\",\n          \"type\": \"bool\"\n        }\n      ],\n      \"payable\": true,\n      \"stateMutability\": \"payable\",\n      \"type\": \"function\"\n    },\n    {\n      \"constant\": true,\n      \"inputs\": [],\n      \"name\": \"accessCharge\",\n      \"outputs\": [\n        {\n          \"name\": \"\",\n          \"type\": \"uint256\"\n        }\n      ],\n      \"payable\": false,\n      \"stateMutability\": \"view\",\n      \"type\": \"function\"\n    },\n    {\n      \"constant\": false,\n      \"inputs\": [\n        {\n          \"name\": \"newCreator\",\n          \"type\": \"address\"\n        }\n      ],\n      \"name\": \"transferCreatorship\",\n      \"outputs\": [],\n      \"payable\": false,\n      \"stateMutability\": \"nonpayable\",\n      \"type\": \"function\"\n    },\n    {\n      \"constant\": true,\n      \"inputs\": [\n        {\n          \"name\": \"\",\n          \"type\": \"uint256\"\n        }\n      ],\n      \"name\": \"versionHashes\",\n      \"outputs\": [\n        {\n          \"name\": \"\",\n          \"type\": \"bytes32\"\n        }\n      ],\n      \"payable\": false,\n      \"stateMutability\": \"view\",\n      \"type\": \"function\"\n    },\n    {\n      \"constant\": false,\n      \"inputs\": [\n        {\n          \"name\": \"status_code\",\n          \"type\": \"int256\"\n        }\n      ],\n      \"name\": \"updateStatus\",\n      \"outputs\": [\n        {\n          \"name\": \"\",\n          \"type\": \"int256\"\n        }\n      ],\n      \"payable\": false,\n      \"stateMutability\": \"nonpayable\",\n      \"type\": \"function\"\n    },\n    {\n      \"constant\": false,\n      \"inputs\": [\n        {\n          \"name\": \"level\",\n          \"type\": \"uint8\"\n        },\n        {\n          \"name\": \"custom_values\",\n          \"type\": \"bytes32[]\"\n        },\n        {\n          \"name\": \"stakeholders\",\n          \"type\": \"address[]\"\n        }\n      ],\n      \"name\": \"getAccessCharge\",\n      \"outputs\": [\n        {\n          \"name\": \"\",\n          \"type\": \"uint256\"\n        }\n      ],\n      \"payable\": false,\n      \"stateMutability\": \"nonpayable\",\n      \"type\": \"function\"\n    },\n    {\n      \"constant\": true,\n      \"inputs\": [],\n      \"name\": \"owner\",\n      \"outputs\": [\n        {\n          \"name\": \"\",\n          \"type\": \"address\"\n        }\n      ],\n      \"payable\": false,\n      \"stateMutability\": \"view\",\n      \"type\": \"function\"\n    },\n    {\n      \"constant\": true,\n      \"inputs\": [],\n      \"name\": \"requestID\",\n      \"outputs\": [\n        {\n          \"name\": \"\",\n          \"type\": \"uint256\"\n        }\n      ],\n      \"payable\": false,\n      \"stateMutability\": \"view\",\n      \"type\": \"function\"\n    },\n    {\n      \"constant\": false,\n      \"inputs\": [\n        {\n          \"name\": \"level\",\n          \"type\": \"uint8\"\n        },\n        {\n          \"name\": \"pke_requestor\",\n          \"type\": \"string\"\n        },\n        {\n          \"name\": \"pke_AFGH\",\n          \"type\": \"string\"\n        },\n        {\n          \"name\": \"custom_values\",\n          \"type\": \"bytes32[]\"\n        },\n        {\n          \"name\": \"stakeholders\",\n          \"type\": \"address[]\"\n        }\n      ],\n      \"name\": \"accessRequest\",\n      \"outputs\": [\n        {\n          \"name\": \"\",\n          \"type\": \"bool\"\n        }\n      ],\n      \"payable\": true,\n      \"stateMutability\": \"payable\",\n      \"type\": \"function\"\n    },\n    {\n      \"constant\": true,\n      \"inputs\": [],\n      \"name\": \"libraryAddress\",\n      \"outputs\": [\n        {\n          \"name\": \"\",\n          \"type\": \"address\"\n        }\n      ],\n      \"payable\": false,\n      \"stateMutability\": \"view\",\n      \"type\": \"function\"\n    },\n    {\n      \"constant\": false,\n      \"inputs\": [],\n      \"name\": \"updateRequest\",\n      \"outputs\": [],\n      \"payable\": false,\n      \"stateMutability\": \"nonpayable\",\n      \"type\": \"function\"\n    },\n    {\n      \"constant\": false,\n      \"inputs\": [\n        {\n          \"name\": \"address_KMS\",\n          \"type\": \"address\"\n        }\n      ],\n      \"name\": \"setAddressKMS\",\n      \"outputs\": [],\n      \"payable\": false,\n      \"stateMutability\": \"nonpayable\",\n      \"type\": \"function\"\n    },\n    {\n      \"constant\": true,\n      \"inputs\": [],\n      \"name\": \"canPublish\",\n      \"outputs\": [\n        {\n          \"name\": \"\",\n          \"type\": \"bool\"\n        }\n      ],\n      \"payable\": false,\n      \"stateMutability\": \"view\",\n      \"type\": \"function\"\n    },\n    {\n      \"constant\": true,\n      \"inputs\": [],\n      \"name\": \"STATUS_REVIEW\",\n      \"outputs\": [\n        {\n          \"name\": \"\",\n          \"type\": \"bytes32\"\n        }\n      ],\n      \"payable\": false,\n      \"stateMutability\": \"view\",\n      \"type\": \"function\"\n    },\n    {\n      \"constant\": true,\n      \"inputs\": [],\n      \"name\": \"objectHash\",\n      \"outputs\": [\n        {\n          \"name\": \"\",\n          \"type\": \"bytes32\"\n        }\n      ],\n      \"payable\": false,\n      \"stateMutability\": \"view\",\n      \"type\": \"function\"\n    },\n    {\n      \"constant\": false,\n      \"inputs\": [\n        {\n          \"name\": \"addr\",\n          \"type\": \"address\"\n        }\n      ],\n      \"name\": \"setContentContractAddress\",\n      \"outputs\": [],\n      \"payable\": false,\n      \"stateMutability\": \"nonpayable\",\n      \"type\": \"function\"\n    },\n    {\n      \"constant\": false,\n      \"inputs\": [\n        {\n          \"name\": \"request_ID\",\n          \"type\": \"uint256\"\n        },\n        {\n          \"name\": \"access_granted\",\n          \"type\": \"bool\"\n        },\n        {\n          \"name\": \"re_key\",\n          \"type\": \"string\"\n        },\n        {\n          \"name\": \"encrypted_AES_key\",\n          \"type\": \"string\"\n        }\n      ],\n      \"name\": \"accessGrant\",\n      \"outputs\": [\n        {\n          \"name\": \"\",\n          \"type\": \"bool\"\n        }\n      ],\n      \"payable\": false,\n      \"stateMutability\": \"nonpayable\",\n      \"type\": \"function\"\n    },\n    {\n      \"constant\": false,\n      \"inputs\": [\n        {\n          \"name\": \"_objectHash\",\n          \"type\": \"bytes32\"\n        }\n      ],\n      \"name\": \"commit\",\n      \"outputs\": [],\n      \"payable\": false,\n      \"stateMutability\": \"nonpayable\",\n      \"type\": \"function\"\n    },\n    {\n      \"constant\": false,\n      \"inputs\": [\n        {\n          \"name\": \"newOwner\",\n          \"type\": \"address\"\n        }\n      ],\n      \"name\": \"transferOwnership\",\n      \"outputs\": [],\n      \"payable\": false,\n      \"stateMutability\": \"nonpayable\",\n      \"type\": \"function\"\n    },\n    {\n      \"constant\": false,\n      \"inputs\": [\n        {\n          \"name\": \"charge\",\n          \"type\": \"uint256\"\n        }\n      ],\n      \"name\": \"setAccessCharge\",\n      \"outputs\": [\n        {\n          \"name\": \"\",\n          \"type\": \"uint256\"\n        }\n      ],\n      \"payable\": false,\n      \"stateMutability\": \"nonpayable\",\n      \"type\": \"function\"\n    },\n    {\n      \"constant\": true,\n      \"inputs\": [],\n      \"name\": \"statusDescription\",\n      \"outputs\": [\n        {\n          \"name\": \"\",\n          \"type\": \"bytes32\"\n        }\n      ],\n      \"payable\": false,\n      \"stateMutability\": \"view\",\n      \"type\": \"function\"\n    },\n    {\n      \"inputs\": [\n        {\n          \"name\": \"content_type\",\n          \"type\": \"address\"\n        }\n      ],\n      \"payable\": true,\n      \"stateMutability\": \"payable\",\n      \"type\": \"constructor\"\n    },\n    {\n      \"payable\": true,\n      \"stateMutability\": \"payable\",\n      \"type\": \"fallback\"\n    },\n    {\n      \"anonymous\": false,\n      \"inputs\": [\n        {\n          \"indexed\": false,\n          \"name\": \"containingLibrary\",\n          \"type\": \"address\"\n        }\n      ],\n      \"name\": \"ContentObjectCreate\",\n      \"type\": \"event\"\n    },\n    {\n      \"anonymous\": false,\n      \"inputs\": [\n        {\n          \"indexed\": false,\n          \"name\": \"contentType\",\n          \"type\": \"address\"\n        },\n        {\n          \"indexed\": false,\n          \"name\": \"contentContractAddress\",\n          \"type\": \"address\"\n        }\n      ],\n      \"name\": \"SetContentType\",\n      \"type\": \"event\"\n    },\n    {\n      \"anonymous\": false,\n      \"inputs\": [\n        {\n          \"indexed\": false,\n          \"name\": \"requestID\",\n          \"type\": \"uint256\"\n        },\n        {\n          \"indexed\": false,\n          \"name\": \"level\",\n          \"type\": \"uint8\"\n        },\n        {\n          \"indexed\": false,\n          \"name\": \"contentHash\",\n          \"type\": \"bytes32\"\n        },\n        {\n          \"indexed\": false,\n          \"name\": \"pkeRequestor\",\n          \"type\": \"string\"\n        },\n        {\n          \"indexed\": false,\n          \"name\": \"pkeAFGH\",\n          \"type\": \"string\"\n        }\n      ],\n      \"name\": \"AccessRequest\",\n      \"type\": \"event\"\n    },\n    {\n      \"anonymous\": false,\n      \"inputs\": [\n        {\n          \"indexed\": false,\n          \"name\": \"requestID\",\n          \"type\": \"uint256\"\n        },\n        {\n          \"indexed\": false,\n          \"name\": \"label\",\n          \"type\": \"string\"\n        },\n        {\n          \"indexed\": false,\n          \"name\": \"payee\",\n          \"type\": \"address\"\n        },\n        {\n          \"indexed\": false,\n          \"name\": \"amount\",\n          \"type\": \"uint256\"\n        }\n      ],\n      \"name\": \"LogPayment\",\n      \"type\": \"event\"\n    },\n    {\n      \"anonymous\": false,\n      \"inputs\": [\n        {\n          \"indexed\": false,\n          \"name\": \"requestID\",\n          \"type\": \"uint256\"\n        },\n        {\n          \"indexed\": false,\n          \"name\": \"access_granted\",\n          \"type\": \"bool\"\n        },\n        {\n          \"indexed\": false,\n          \"name\": \"reKey\",\n          \"type\": \"string\"\n        },\n        {\n          \"indexed\": false,\n          \"name\": \"encryptedAESKey\",\n          \"type\": \"string\"\n        }\n      ],\n      \"name\": \"AccessGrant\",\n      \"type\": \"event\"\n    },\n    {\n      \"anonymous\": false,\n      \"inputs\": [\n        {\n          \"indexed\": false,\n          \"name\": \"customValue\",\n          \"type\": \"bytes32\"\n        }\n      ],\n      \"name\": \"AccessRequestValue\",\n      \"type\": \"event\"\n    },\n    {\n      \"anonymous\": false,\n      \"inputs\": [\n        {\n          \"indexed\": false,\n          \"name\": \"stakeholder\",\n          \"type\": \"address\"\n        }\n      ],\n      \"name\": \"AccessRequestStakeholder\",\n      \"type\": \"event\"\n    },\n    {\n      \"anonymous\": false,\n      \"inputs\": [\n        {\n          \"indexed\": false,\n          \"name\": \"requestID\",\n          \"type\": \"uint256\"\n        },\n        {\n          \"indexed\": false,\n          \"name\": \"scorePct\",\n          \"type\": \"uint256\"\n        },\n        {\n          \"indexed\": false,\n          \"name\": \"mlOutHash\",\n          \"type\": \"bytes32\"\n        },\n        {\n          \"indexed\": false,\n          \"name\": \"customContractResult\",\n          \"type\": \"bool\"\n        }\n      ],\n      \"name\": \"AccessComplete\",\n      \"type\": \"event\"\n    },\n    {\n      \"anonymous\": false,\n      \"inputs\": [\n        {\n          \"indexed\": false,\n          \"name\": \"contentContractAddress\",\n          \"type\": \"address\"\n        }\n      ],\n      \"name\": \"SetContentContract\",\n      \"type\": \"event\"\n    },\n    {\n      \"anonymous\": false,\n      \"inputs\": [\n        {\n          \"indexed\": false,\n          \"name\": \"accessCharge\",\n          \"type\": \"uint256\"\n        }\n      ],\n      \"name\": \"SetAccessCharge\",\n      \"type\": \"event\"\n    },\n    {\n      \"anonymous\": false,\n      \"inputs\": [\n        {\n          \"indexed\": false,\n          \"name\": \"level\",\n          \"type\": \"uint8\"\n        },\n        {\n          \"indexed\": false,\n          \"name\": \"accessCharge\",\n          \"type\": \"uint256\"\n        }\n      ],\n      \"name\": \"GetAccessCharge\",\n      \"type\": \"event\"\n    },\n    {\n      \"anonymous\": false,\n      \"inputs\": [\n        {\n          \"indexed\": false,\n          \"name\": \"accessCharge\",\n          \"type\": \"uint256\"\n        },\n        {\n          \"indexed\": false,\n          \"name\": \"amountProvided\",\n          \"type\": \"uint256\"\n        }\n      ],\n      \"name\": \"InsufficientFunds\",\n      \"type\": \"event\"\n    },\n    {\n      \"anonymous\": false,\n      \"inputs\": [\n        {\n          \"indexed\": false,\n          \"name\": \"statusCode\",\n          \"type\": \"int256\"\n        }\n      ],\n      \"name\": \"SetStatusCode\",\n      \"type\": \"event\"\n    },\n    {\n      \"anonymous\": false,\n      \"inputs\": [\n        {\n          \"indexed\": false,\n          \"name\": \"requestStatus\",\n          \"type\": \"bool\"\n        },\n        {\n          \"indexed\": false,\n          \"name\": \"statusCode\",\n          \"type\": \"int256\"\n        },\n        {\n          \"indexed\": false,\n          \"name\": \"objectHash\",\n          \"type\": \"bytes32\"\n        }\n      ],\n      \"name\": \"Publish\",\n      \"type\": \"event\"\n    },\n    {\n      \"anonymous\": false,\n      \"inputs\": [\n        {\n          \"indexed\": false,\n          \"name\": \"custom_contract\",\n          \"type\": \"address\"\n        }\n      ],\n      \"name\": \"InvokeCustomPreHook\",\n      \"type\": \"event\"\n    },\n    {\n      \"anonymous\": false,\n      \"inputs\": [\n        {\n          \"indexed\": false,\n          \"name\": \"custom_contract\",\n          \"type\": \"address\"\n        },\n        {\n          \"indexed\": false,\n          \"name\": \"result\",\n          \"type\": \"uint256\"\n        }\n      ],\n      \"name\": \"ReturnCustomHook\",\n      \"type\": \"event\"\n    },\n    {\n      \"anonymous\": false,\n      \"inputs\": [\n        {\n          \"indexed\": false,\n          \"name\": \"custom_contract\",\n          \"type\": \"address\"\n        }\n      ],\n      \"name\": \"InvokeCustomPostHook\",\n      \"type\": \"event\"\n    },\n    {\n      \"anonymous\": false,\n      \"inputs\": [\n        {\n          \"indexed\": false,\n          \"name\": \"objectHash\",\n          \"type\": \"bytes32\"\n        }\n      ],\n      \"name\": \"CommitPending\",\n      \"type\": \"event\"\n    },\n    {\n      \"anonymous\": false,\n      \"inputs\": [\n        {\n          \"indexed\": false,\n          \"name\": \"objectHash\",\n          \"type\": \"bytes32\"\n        }\n      ],\n      \"name\": \"Commit\",\n      \"type\": \"event\"\n    },\n    {\n      \"anonymous\": false,\n      \"inputs\": [\n        {\n          \"indexed\": false,\n          \"name\": \"objectHash\",\n          \"type\": \"bytes32\"\n        }\n      ],\n      \"name\": \"UpdateRequest\",\n      \"type\": \"event\"\n    }\n  ],\n  \"event\": {\n    \"to\": \"0x77A643B34D3DbafB4f5e380172613096637Fd02b\",\n    \"from\": \"0xc2635Ab30Fc19F616332c6d2d7F14cdAf7ce1965\",\n    \"contractAddress\": null,\n    \"transactionIndex\": 0,\n    \"gasUsed\": {\n      \"_hex\": \"0x181c3\"\n    },\n    \"logsBloom\": \"0x00000000000000000000000000000000000000000000000000000000000000000000000000000000002000000000000000000000000000000000000000000000000000000000000004000000000000000000000000000000000004000000000000400000000000000000000000000000000000000000000000000000000000000000000000000000004000000000000000000000000000000000000000000000000000000000000000000000000000000000000000000000000000000000000000000000000000000000000000000000000000000000000000000000000000000000000000000000000000000000000000000000000000000000002000000000\",\n    \"blockHash\": \"0xbbf9bcaf33734a9e3361b5bd98dacfe1fe75823d9d64e1cdab22f669193f5925\",\n    \"transactionHash\": \"0x9d92e56441e259f15dad29e965c733e2c0e9dc99f7c24dfef75859543b138964\",\n    \"logs\": [\n      {\n        \"transactionIndex\": 0,\n        \"blockNumber\": 752,\n        \"transactionHash\": \"0x9d92e56441e259f15dad29e965c733e2c0e9dc99f7c24dfef75859543b138964\",\n        \"address\": \"0x77A643B34D3DbafB4f5e380172613096637Fd02b\",\n        \"topics\": [\n          \"0x089a6f1788a3c353423e1be4ba12533bdde7d908bb41abeee185af0acb3df562\"\n        ],\n        \"data\": \"0x00000000000000000000000000000000000000000000000000000000000000010000000000000000000000000000000000000000000000000000000000000000000000000000000000000000000000000000000000000000000000000000000000000000000000000000000000000000000000000000000000000000000000a000000000000000000000000000000000000000000000000000000000000001600000000000000000000000000000000000000000000000000000000000000084307830346662626561336262633038303466303565383233643233313232383538666137323164663765396331363939336238316362373761323961373236393361303733626562633030383730343737323036626531623830383037306162316162666231366365616264613963623535643633623332653734396230623162633033000000000000000000000000000000000000000000000000000000000000000000000000000000000000000000000000000000000000000000000000\",\n        \"logIndex\": 0,\n        \"blockHash\": \"0xbbf9bcaf33734a9e3361b5bd98dacfe1fe75823d9d64e1cdab22f669193f5925\",\n        \"transactionLogIndex\": 0,\n        \"name\": \"AccessRequest\",\n        \"signature\": \"AccessRequest(uint256,uint8,bytes32,string,string)\",\n        \"topic\": \"0x089a6f1788a3c353423e1be4ba12533bdde7d908bb41abeee185af0acb3df562\",\n        \"values\": {\n          \"0\": {\n            \"_hex\": \"0x01\"\n          },\n          \"1\": 0,\n          \"2\": \"0x0000000000000000000000000000000000000000000000000000000000000000\",\n          \"3\": \"0x04fbbea3bbc0804f05e823d23122858fa721df7e9c16993b81cb77a29a72693a073bebc00870477206be1b808070ab1abfb16ceabda9cb55d63b32e749b0b1bc03\",\n          \"4\": \"\",\n          \"requestID\": {\n            \"_hex\": \"0x01\"\n          },\n          \"level\": 0,\n          \"contentHash\": \"0x0000000000000000000000000000000000000000000000000000000000000000\",\n          \"pkeRequestor\": \"0x04fbbea3bbc0804f05e823d23122858fa721df7e9c16993b81cb77a29a72693a073bebc00870477206be1b808070ab1abfb16ceabda9cb55d63b32e749b0b1bc03\",\n          \"pkeAFGH\": \"\",\n          \"length\": 5\n        }\n      }\n    ],\n    \"blockNumber\": 752,\n    \"confirmations\": 2,\n    \"cumulativeGasUsed\": {\n      \"_hex\": \"0x181c3\"\n    },\n    \"status\": 1,\n    \"byzantium\": true\n  },\n  \"eventName\": \"AccessRequest\"\n});",
    "result": "{\n  \"name\": \"AccessRequest\",\n  \"signature\": \"AccessRequest(uint256,uint8,bytes32,string,string)\",\n  \"topic\": \"0x089a6f1788a3c353423e1be4ba12533bdde7d908bb41abeee185af0acb3df562\",\n  \"values\": {\n    \"0\": {\n      \"_hex\": \"0x01\"\n    },\n    \"1\": 0,\n    \"2\": \"0x0000000000000000000000000000000000000000000000000000000000000000\",\n    \"3\": \"0x04fbbea3bbc0804f05e823d23122858fa721df7e9c16993b81cb77a29a72693a073bebc00870477206be1b808070ab1abfb16ceabda9cb55d63b32e749b0b1bc03\",\n    \"4\": \"\",\n    \"requestID\": {\n      \"_hex\": \"0x01\"\n    },\n    \"level\": 0,\n    \"contentHash\": \"0x0000000000000000000000000000000000000000000000000000000000000000\",\n    \"pkeRequestor\": \"0x04fbbea3bbc0804f05e823d23122858fa721df7e9c16993b81cb77a29a72693a073bebc00870477206be1b808070ab1abfb16ceabda9cb55d63b32e749b0b1bc03\",\n    \"pkeAFGH\": \"\",\n    \"length\": 5\n  }\n}"
  },
  {
    "signature": "async ExtractEventFromLogs({\n  \"abi\": [\n    {\n      \"constant\": true,\n      \"inputs\": [],\n      \"name\": \"STATUS_PUBLISHED\",\n      \"outputs\": [\n        {\n          \"name\": \"\",\n          \"type\": \"bytes32\"\n        }\n      ],\n      \"payable\": false,\n      \"stateMutability\": \"view\",\n      \"type\": \"function\"\n    },\n    {\n      \"constant\": true,\n      \"inputs\": [],\n      \"name\": \"creator\",\n      \"outputs\": [\n        {\n          \"name\": \"\",\n          \"type\": \"address\"\n        }\n      ],\n      \"payable\": false,\n      \"stateMutability\": \"view\",\n      \"type\": \"function\"\n    },\n    {\n      \"constant\": false,\n      \"inputs\": [],\n      \"name\": \"publish\",\n      \"outputs\": [\n        {\n          \"name\": \"\",\n          \"type\": \"bool\"\n        }\n      ],\n      \"payable\": true,\n      \"stateMutability\": \"payable\",\n      \"type\": \"function\"\n    },\n    {\n      \"constant\": false,\n      \"inputs\": [\n        {\n          \"name\": \"request_ID\",\n          \"type\": \"uint256\"\n        },\n        {\n          \"name\": \"payee\",\n          \"type\": \"address\"\n        },\n        {\n          \"name\": \"label\",\n          \"type\": \"string\"\n        },\n        {\n          \"name\": \"amount\",\n          \"type\": \"uint256\"\n        }\n      ],\n      \"name\": \"processRequestPayment\",\n      \"outputs\": [\n        {\n          \"name\": \"\",\n          \"type\": \"bool\"\n        }\n      ],\n      \"payable\": false,\n      \"stateMutability\": \"nonpayable\",\n      \"type\": \"function\"\n    },\n    {\n      \"constant\": true,\n      \"inputs\": [\n        {\n          \"name\": \"\",\n          \"type\": \"uint256\"\n        }\n      ],\n      \"name\": \"requestMap\",\n      \"outputs\": [\n        {\n          \"name\": \"originator\",\n          \"type\": \"address\"\n        },\n        {\n          \"name\": \"amountPaid\",\n          \"type\": \"uint256\"\n        },\n        {\n          \"name\": \"status\",\n          \"type\": \"int8\"\n        },\n        {\n          \"name\": \"settled\",\n          \"type\": \"uint256\"\n        }\n      ],\n      \"payable\": false,\n      \"stateMutability\": \"view\",\n      \"type\": \"function\"\n    },\n    {\n      \"constant\": true,\n      \"inputs\": [],\n      \"name\": \"contentContractAddress\",\n      \"outputs\": [\n        {\n          \"name\": \"\",\n          \"type\": \"address\"\n        }\n      ],\n      \"payable\": false,\n      \"stateMutability\": \"view\",\n      \"type\": \"function\"\n    },\n    {\n      \"constant\": true,\n      \"inputs\": [],\n      \"name\": \"statusCode\",\n      \"outputs\": [\n        {\n          \"name\": \"\",\n          \"type\": \"int256\"\n        }\n      ],\n      \"payable\": false,\n      \"stateMutability\": \"view\",\n      \"type\": \"function\"\n    },\n    {\n      \"constant\": true,\n      \"inputs\": [],\n      \"name\": \"addressKMS\",\n      \"outputs\": [\n        {\n          \"name\": \"\",\n          \"type\": \"address\"\n        }\n      ],\n      \"payable\": false,\n      \"stateMutability\": \"view\",\n      \"type\": \"function\"\n    },\n    {\n      \"constant\": true,\n      \"inputs\": [],\n      \"name\": \"contentType\",\n      \"outputs\": [\n        {\n          \"name\": \"\",\n          \"type\": \"address\"\n        }\n      ],\n      \"payable\": false,\n      \"stateMutability\": \"view\",\n      \"type\": \"function\"\n    },\n    {\n      \"constant\": true,\n      \"inputs\": [\n        {\n          \"name\": \"status_code\",\n          \"type\": \"int256\"\n        }\n      ],\n      \"name\": \"statusCodeDescription\",\n      \"outputs\": [\n        {\n          \"name\": \"\",\n          \"type\": \"bytes32\"\n        }\n      ],\n      \"payable\": false,\n      \"stateMutability\": \"view\",\n      \"type\": \"function\"\n    },\n    {\n      \"constant\": true,\n      \"inputs\": [\n        {\n          \"name\": \"level\",\n          \"type\": \"uint8\"\n        },\n        {\n          \"name\": \"custom_values\",\n          \"type\": \"bytes32[]\"\n        },\n        {\n          \"name\": \"stakeholders\",\n          \"type\": \"address[]\"\n        }\n      ],\n      \"name\": \"getAccessInfo\",\n      \"outputs\": [\n        {\n          \"name\": \"\",\n          \"type\": \"int8\"\n        },\n        {\n          \"name\": \"\",\n          \"type\": \"uint256\"\n        }\n      ],\n      \"payable\": false,\n      \"stateMutability\": \"view\",\n      \"type\": \"function\"\n    },\n    {\n      \"constant\": false,\n      \"inputs\": [],\n      \"name\": \"kill\",\n      \"outputs\": [],\n      \"payable\": false,\n      \"stateMutability\": \"nonpayable\",\n      \"type\": \"function\"\n    },\n    {\n      \"constant\": true,\n      \"inputs\": [],\n      \"name\": \"STATUS_DRAFT\",\n      \"outputs\": [\n        {\n          \"name\": \"\",\n          \"type\": \"bytes32\"\n        }\n      ],\n      \"payable\": false,\n      \"stateMutability\": \"view\",\n      \"type\": \"function\"\n    },\n    {\n      \"constant\": false,\n      \"inputs\": [\n        {\n          \"name\": \"status_code\",\n          \"type\": \"int256\"\n        }\n      ],\n      \"name\": \"setStatusCode\",\n      \"outputs\": [\n        {\n          \"name\": \"\",\n          \"type\": \"int256\"\n        }\n      ],\n      \"payable\": false,\n      \"stateMutability\": \"nonpayable\",\n      \"type\": \"function\"\n    },\n    {\n      \"constant\": true,\n      \"inputs\": [],\n      \"name\": \"version\",\n      \"outputs\": [\n        {\n          \"name\": \"\",\n          \"type\": \"bytes32\"\n        }\n      ],\n      \"payable\": false,\n      \"stateMutability\": \"view\",\n      \"type\": \"function\"\n    },\n    {\n      \"constant\": false,\n      \"inputs\": [\n        {\n          \"name\": \"request_ID\",\n          \"type\": \"uint256\"\n        },\n        {\n          \"name\": \"score_pct\",\n          \"type\": \"uint256\"\n        },\n        {\n          \"name\": \"ml_out_hash\",\n          \"type\": \"bytes32\"\n        }\n      ],\n      \"name\": \"accessComplete\",\n      \"outputs\": [\n        {\n          \"name\": \"\",\n          \"type\": \"bool\"\n        }\n      ],\n      \"payable\": true,\n      \"stateMutability\": \"payable\",\n      \"type\": \"function\"\n    },\n    {\n      \"constant\": true,\n      \"inputs\": [],\n      \"name\": \"accessCharge\",\n      \"outputs\": [\n        {\n          \"name\": \"\",\n          \"type\": \"uint256\"\n        }\n      ],\n      \"payable\": false,\n      \"stateMutability\": \"view\",\n      \"type\": \"function\"\n    },\n    {\n      \"constant\": false,\n      \"inputs\": [\n        {\n          \"name\": \"newCreator\",\n          \"type\": \"address\"\n        }\n      ],\n      \"name\": \"transferCreatorship\",\n      \"outputs\": [],\n      \"payable\": false,\n      \"stateMutability\": \"nonpayable\",\n      \"type\": \"function\"\n    },\n    {\n      \"constant\": true,\n      \"inputs\": [\n        {\n          \"name\": \"\",\n          \"type\": \"uint256\"\n        }\n      ],\n      \"name\": \"versionHashes\",\n      \"outputs\": [\n        {\n          \"name\": \"\",\n          \"type\": \"bytes32\"\n        }\n      ],\n      \"payable\": false,\n      \"stateMutability\": \"view\",\n      \"type\": \"function\"\n    },\n    {\n      \"constant\": false,\n      \"inputs\": [\n        {\n          \"name\": \"status_code\",\n          \"type\": \"int256\"\n        }\n      ],\n      \"name\": \"updateStatus\",\n      \"outputs\": [\n        {\n          \"name\": \"\",\n          \"type\": \"int256\"\n        }\n      ],\n      \"payable\": false,\n      \"stateMutability\": \"nonpayable\",\n      \"type\": \"function\"\n    },\n    {\n      \"constant\": false,\n      \"inputs\": [\n        {\n          \"name\": \"level\",\n          \"type\": \"uint8\"\n        },\n        {\n          \"name\": \"custom_values\",\n          \"type\": \"bytes32[]\"\n        },\n        {\n          \"name\": \"stakeholders\",\n          \"type\": \"address[]\"\n        }\n      ],\n      \"name\": \"getAccessCharge\",\n      \"outputs\": [\n        {\n          \"name\": \"\",\n          \"type\": \"uint256\"\n        }\n      ],\n      \"payable\": false,\n      \"stateMutability\": \"nonpayable\",\n      \"type\": \"function\"\n    },\n    {\n      \"constant\": true,\n      \"inputs\": [],\n      \"name\": \"owner\",\n      \"outputs\": [\n        {\n          \"name\": \"\",\n          \"type\": \"address\"\n        }\n      ],\n      \"payable\": false,\n      \"stateMutability\": \"view\",\n      \"type\": \"function\"\n    },\n    {\n      \"constant\": true,\n      \"inputs\": [],\n      \"name\": \"requestID\",\n      \"outputs\": [\n        {\n          \"name\": \"\",\n          \"type\": \"uint256\"\n        }\n      ],\n      \"payable\": false,\n      \"stateMutability\": \"view\",\n      \"type\": \"function\"\n    },\n    {\n      \"constant\": false,\n      \"inputs\": [\n        {\n          \"name\": \"level\",\n          \"type\": \"uint8\"\n        },\n        {\n          \"name\": \"pke_requestor\",\n          \"type\": \"string\"\n        },\n        {\n          \"name\": \"pke_AFGH\",\n          \"type\": \"string\"\n        },\n        {\n          \"name\": \"custom_values\",\n          \"type\": \"bytes32[]\"\n        },\n        {\n          \"name\": \"stakeholders\",\n          \"type\": \"address[]\"\n        }\n      ],\n      \"name\": \"accessRequest\",\n      \"outputs\": [\n        {\n          \"name\": \"\",\n          \"type\": \"bool\"\n        }\n      ],\n      \"payable\": true,\n      \"stateMutability\": \"payable\",\n      \"type\": \"function\"\n    },\n    {\n      \"constant\": true,\n      \"inputs\": [],\n      \"name\": \"libraryAddress\",\n      \"outputs\": [\n        {\n          \"name\": \"\",\n          \"type\": \"address\"\n        }\n      ],\n      \"payable\": false,\n      \"stateMutability\": \"view\",\n      \"type\": \"function\"\n    },\n    {\n      \"constant\": false,\n      \"inputs\": [],\n      \"name\": \"updateRequest\",\n      \"outputs\": [],\n      \"payable\": false,\n      \"stateMutability\": \"nonpayable\",\n      \"type\": \"function\"\n    },\n    {\n      \"constant\": false,\n      \"inputs\": [\n        {\n          \"name\": \"address_KMS\",\n          \"type\": \"address\"\n        }\n      ],\n      \"name\": \"setAddressKMS\",\n      \"outputs\": [],\n      \"payable\": false,\n      \"stateMutability\": \"nonpayable\",\n      \"type\": \"function\"\n    },\n    {\n      \"constant\": true,\n      \"inputs\": [],\n      \"name\": \"canPublish\",\n      \"outputs\": [\n        {\n          \"name\": \"\",\n          \"type\": \"bool\"\n        }\n      ],\n      \"payable\": false,\n      \"stateMutability\": \"view\",\n      \"type\": \"function\"\n    },\n    {\n      \"constant\": true,\n      \"inputs\": [],\n      \"name\": \"STATUS_REVIEW\",\n      \"outputs\": [\n        {\n          \"name\": \"\",\n          \"type\": \"bytes32\"\n        }\n      ],\n      \"payable\": false,\n      \"stateMutability\": \"view\",\n      \"type\": \"function\"\n    },\n    {\n      \"constant\": true,\n      \"inputs\": [],\n      \"name\": \"objectHash\",\n      \"outputs\": [\n        {\n          \"name\": \"\",\n          \"type\": \"bytes32\"\n        }\n      ],\n      \"payable\": false,\n      \"stateMutability\": \"view\",\n      \"type\": \"function\"\n    },\n    {\n      \"constant\": false,\n      \"inputs\": [\n        {\n          \"name\": \"addr\",\n          \"type\": \"address\"\n        }\n      ],\n      \"name\": \"setContentContractAddress\",\n      \"outputs\": [],\n      \"payable\": false,\n      \"stateMutability\": \"nonpayable\",\n      \"type\": \"function\"\n    },\n    {\n      \"constant\": false,\n      \"inputs\": [\n        {\n          \"name\": \"request_ID\",\n          \"type\": \"uint256\"\n        },\n        {\n          \"name\": \"access_granted\",\n          \"type\": \"bool\"\n        },\n        {\n          \"name\": \"re_key\",\n          \"type\": \"string\"\n        },\n        {\n          \"name\": \"encrypted_AES_key\",\n          \"type\": \"string\"\n        }\n      ],\n      \"name\": \"accessGrant\",\n      \"outputs\": [\n        {\n          \"name\": \"\",\n          \"type\": \"bool\"\n        }\n      ],\n      \"payable\": false,\n      \"stateMutability\": \"nonpayable\",\n      \"type\": \"function\"\n    },\n    {\n      \"constant\": false,\n      \"inputs\": [\n        {\n          \"name\": \"_objectHash\",\n          \"type\": \"bytes32\"\n        }\n      ],\n      \"name\": \"commit\",\n      \"outputs\": [],\n      \"payable\": false,\n      \"stateMutability\": \"nonpayable\",\n      \"type\": \"function\"\n    },\n    {\n      \"constant\": false,\n      \"inputs\": [\n        {\n          \"name\": \"newOwner\",\n          \"type\": \"address\"\n        }\n      ],\n      \"name\": \"transferOwnership\",\n      \"outputs\": [],\n      \"payable\": false,\n      \"stateMutability\": \"nonpayable\",\n      \"type\": \"function\"\n    },\n    {\n      \"constant\": false,\n      \"inputs\": [\n        {\n          \"name\": \"charge\",\n          \"type\": \"uint256\"\n        }\n      ],\n      \"name\": \"setAccessCharge\",\n      \"outputs\": [\n        {\n          \"name\": \"\",\n          \"type\": \"uint256\"\n        }\n      ],\n      \"payable\": false,\n      \"stateMutability\": \"nonpayable\",\n      \"type\": \"function\"\n    },\n    {\n      \"constant\": true,\n      \"inputs\": [],\n      \"name\": \"statusDescription\",\n      \"outputs\": [\n        {\n          \"name\": \"\",\n          \"type\": \"bytes32\"\n        }\n      ],\n      \"payable\": false,\n      \"stateMutability\": \"view\",\n      \"type\": \"function\"\n    },\n    {\n      \"inputs\": [\n        {\n          \"name\": \"content_type\",\n          \"type\": \"address\"\n        }\n      ],\n      \"payable\": true,\n      \"stateMutability\": \"payable\",\n      \"type\": \"constructor\"\n    },\n    {\n      \"payable\": true,\n      \"stateMutability\": \"payable\",\n      \"type\": \"fallback\"\n    },\n    {\n      \"anonymous\": false,\n      \"inputs\": [\n        {\n          \"indexed\": false,\n          \"name\": \"containingLibrary\",\n          \"type\": \"address\"\n        }\n      ],\n      \"name\": \"ContentObjectCreate\",\n      \"type\": \"event\"\n    },\n    {\n      \"anonymous\": false,\n      \"inputs\": [\n        {\n          \"indexed\": false,\n          \"name\": \"contentType\",\n          \"type\": \"address\"\n        },\n        {\n          \"indexed\": false,\n          \"name\": \"contentContractAddress\",\n          \"type\": \"address\"\n        }\n      ],\n      \"name\": \"SetContentType\",\n      \"type\": \"event\"\n    },\n    {\n      \"anonymous\": false,\n      \"inputs\": [\n        {\n          \"indexed\": false,\n          \"name\": \"requestID\",\n          \"type\": \"uint256\"\n        },\n        {\n          \"indexed\": false,\n          \"name\": \"level\",\n          \"type\": \"uint8\"\n        },\n        {\n          \"indexed\": false,\n          \"name\": \"contentHash\",\n          \"type\": \"bytes32\"\n        },\n        {\n          \"indexed\": false,\n          \"name\": \"pkeRequestor\",\n          \"type\": \"string\"\n        },\n        {\n          \"indexed\": false,\n          \"name\": \"pkeAFGH\",\n          \"type\": \"string\"\n        }\n      ],\n      \"name\": \"AccessRequest\",\n      \"type\": \"event\"\n    },\n    {\n      \"anonymous\": false,\n      \"inputs\": [\n        {\n          \"indexed\": false,\n          \"name\": \"requestID\",\n          \"type\": \"uint256\"\n        },\n        {\n          \"indexed\": false,\n          \"name\": \"label\",\n          \"type\": \"string\"\n        },\n        {\n          \"indexed\": false,\n          \"name\": \"payee\",\n          \"type\": \"address\"\n        },\n        {\n          \"indexed\": false,\n          \"name\": \"amount\",\n          \"type\": \"uint256\"\n        }\n      ],\n      \"name\": \"LogPayment\",\n      \"type\": \"event\"\n    },\n    {\n      \"anonymous\": false,\n      \"inputs\": [\n        {\n          \"indexed\": false,\n          \"name\": \"requestID\",\n          \"type\": \"uint256\"\n        },\n        {\n          \"indexed\": false,\n          \"name\": \"access_granted\",\n          \"type\": \"bool\"\n        },\n        {\n          \"indexed\": false,\n          \"name\": \"reKey\",\n          \"type\": \"string\"\n        },\n        {\n          \"indexed\": false,\n          \"name\": \"encryptedAESKey\",\n          \"type\": \"string\"\n        }\n      ],\n      \"name\": \"AccessGrant\",\n      \"type\": \"event\"\n    },\n    {\n      \"anonymous\": false,\n      \"inputs\": [\n        {\n          \"indexed\": false,\n          \"name\": \"customValue\",\n          \"type\": \"bytes32\"\n        }\n      ],\n      \"name\": \"AccessRequestValue\",\n      \"type\": \"event\"\n    },\n    {\n      \"anonymous\": false,\n      \"inputs\": [\n        {\n          \"indexed\": false,\n          \"name\": \"stakeholder\",\n          \"type\": \"address\"\n        }\n      ],\n      \"name\": \"AccessRequestStakeholder\",\n      \"type\": \"event\"\n    },\n    {\n      \"anonymous\": false,\n      \"inputs\": [\n        {\n          \"indexed\": false,\n          \"name\": \"requestID\",\n          \"type\": \"uint256\"\n        },\n        {\n          \"indexed\": false,\n          \"name\": \"scorePct\",\n          \"type\": \"uint256\"\n        },\n        {\n          \"indexed\": false,\n          \"name\": \"mlOutHash\",\n          \"type\": \"bytes32\"\n        },\n        {\n          \"indexed\": false,\n          \"name\": \"customContractResult\",\n          \"type\": \"bool\"\n        }\n      ],\n      \"name\": \"AccessComplete\",\n      \"type\": \"event\"\n    },\n    {\n      \"anonymous\": false,\n      \"inputs\": [\n        {\n          \"indexed\": false,\n          \"name\": \"contentContractAddress\",\n          \"type\": \"address\"\n        }\n      ],\n      \"name\": \"SetContentContract\",\n      \"type\": \"event\"\n    },\n    {\n      \"anonymous\": false,\n      \"inputs\": [\n        {\n          \"indexed\": false,\n          \"name\": \"accessCharge\",\n          \"type\": \"uint256\"\n        }\n      ],\n      \"name\": \"SetAccessCharge\",\n      \"type\": \"event\"\n    },\n    {\n      \"anonymous\": false,\n      \"inputs\": [\n        {\n          \"indexed\": false,\n          \"name\": \"level\",\n          \"type\": \"uint8\"\n        },\n        {\n          \"indexed\": false,\n          \"name\": \"accessCharge\",\n          \"type\": \"uint256\"\n        }\n      ],\n      \"name\": \"GetAccessCharge\",\n      \"type\": \"event\"\n    },\n    {\n      \"anonymous\": false,\n      \"inputs\": [\n        {\n          \"indexed\": false,\n          \"name\": \"accessCharge\",\n          \"type\": \"uint256\"\n        },\n        {\n          \"indexed\": false,\n          \"name\": \"amountProvided\",\n          \"type\": \"uint256\"\n        }\n      ],\n      \"name\": \"InsufficientFunds\",\n      \"type\": \"event\"\n    },\n    {\n      \"anonymous\": false,\n      \"inputs\": [\n        {\n          \"indexed\": false,\n          \"name\": \"statusCode\",\n          \"type\": \"int256\"\n        }\n      ],\n      \"name\": \"SetStatusCode\",\n      \"type\": \"event\"\n    },\n    {\n      \"anonymous\": false,\n      \"inputs\": [\n        {\n          \"indexed\": false,\n          \"name\": \"requestStatus\",\n          \"type\": \"bool\"\n        },\n        {\n          \"indexed\": false,\n          \"name\": \"statusCode\",\n          \"type\": \"int256\"\n        },\n        {\n          \"indexed\": false,\n          \"name\": \"objectHash\",\n          \"type\": \"bytes32\"\n        }\n      ],\n      \"name\": \"Publish\",\n      \"type\": \"event\"\n    },\n    {\n      \"anonymous\": false,\n      \"inputs\": [\n        {\n          \"indexed\": false,\n          \"name\": \"custom_contract\",\n          \"type\": \"address\"\n        }\n      ],\n      \"name\": \"InvokeCustomPreHook\",\n      \"type\": \"event\"\n    },\n    {\n      \"anonymous\": false,\n      \"inputs\": [\n        {\n          \"indexed\": false,\n          \"name\": \"custom_contract\",\n          \"type\": \"address\"\n        },\n        {\n          \"indexed\": false,\n          \"name\": \"result\",\n          \"type\": \"uint256\"\n        }\n      ],\n      \"name\": \"ReturnCustomHook\",\n      \"type\": \"event\"\n    },\n    {\n      \"anonymous\": false,\n      \"inputs\": [\n        {\n          \"indexed\": false,\n          \"name\": \"custom_contract\",\n          \"type\": \"address\"\n        }\n      ],\n      \"name\": \"InvokeCustomPostHook\",\n      \"type\": \"event\"\n    },\n    {\n      \"anonymous\": false,\n      \"inputs\": [\n        {\n          \"indexed\": false,\n          \"name\": \"objectHash\",\n          \"type\": \"bytes32\"\n        }\n      ],\n      \"name\": \"CommitPending\",\n      \"type\": \"event\"\n    },\n    {\n      \"anonymous\": false,\n      \"inputs\": [\n        {\n          \"indexed\": false,\n          \"name\": \"objectHash\",\n          \"type\": \"bytes32\"\n        }\n      ],\n      \"name\": \"Commit\",\n      \"type\": \"event\"\n    },\n    {\n      \"anonymous\": false,\n      \"inputs\": [\n        {\n          \"indexed\": false,\n          \"name\": \"objectHash\",\n          \"type\": \"bytes32\"\n        }\n      ],\n      \"name\": \"UpdateRequest\",\n      \"type\": \"event\"\n    }\n  ],\n  \"event\": {\n    \"to\": \"0x61E76Bc8b01352A2b12d8e8949F9c1CDF6ca447D\",\n    \"from\": \"0xc2635Ab30Fc19F616332c6d2d7F14cdAf7ce1965\",\n    \"contractAddress\": null,\n    \"transactionIndex\": 0,\n    \"gasUsed\": {\n      \"_hex\": \"0x1472b\"\n    },\n    \"logsBloom\": \"0x00000000000000000000000000040000000000000000000000000000000000000000000000000000000000000000000000000000000000000000000000000000080000000000000004000000000000000000000000000000000000000000000000400000000000000000000000000000000000000000000000000000000000000000000000000000000000000000000000000000000000000001000000000000000000000000000000000000000000000000000000000000000000000000000000000000000000000000000000000000000000000000000000000000000000000000000000000000000000000000000000000000000000000000002000000000\",\n    \"blockHash\": \"0x68b41eb14c4292bcb75ae53505d39b4fe99489ad2b8d02248ecf67e942740be4\",\n    \"transactionHash\": \"0xd5638438159c2934c8e9ce16a21fd1eb453bf3f0dc8440372af6ff6b12fdaf41\",\n    \"logs\": [\n      {\n        \"transactionIndex\": 0,\n        \"blockNumber\": 756,\n        \"transactionHash\": \"0xd5638438159c2934c8e9ce16a21fd1eb453bf3f0dc8440372af6ff6b12fdaf41\",\n        \"address\": \"0x61E76Bc8b01352A2b12d8e8949F9c1CDF6ca447D\",\n        \"topics\": [\n          \"0x089a6f1788a3c353423e1be4ba12533bdde7d908bb41abeee185af0acb3df562\"\n        ],\n        \"data\": \"0x00000000000000000000000000000000000000000000000000000000000000020000000000000000000000000000000000000000000000000000000000000000000000000000000000000000000000000000000000000000000000000000000000000000000000000000000000000000000000000000000000000000000000a000000000000000000000000000000000000000000000000000000000000001600000000000000000000000000000000000000000000000000000000000000084307830346662626561336262633038303466303565383233643233313232383538666137323164663765396331363939336238316362373761323961373236393361303733626562633030383730343737323036626531623830383037306162316162666231366365616264613963623535643633623332653734396230623162633033000000000000000000000000000000000000000000000000000000000000000000000000000000000000000000000000000000000000000000000000\",\n        \"logIndex\": 0,\n        \"blockHash\": \"0x68b41eb14c4292bcb75ae53505d39b4fe99489ad2b8d02248ecf67e942740be4\",\n        \"transactionLogIndex\": 0,\n        \"name\": \"AccessRequest\",\n        \"signature\": \"AccessRequest(uint256,uint8,bytes32,string,string)\",\n        \"topic\": \"0x089a6f1788a3c353423e1be4ba12533bdde7d908bb41abeee185af0acb3df562\",\n        \"values\": {\n          \"0\": {\n            \"_hex\": \"0x02\"\n          },\n          \"1\": 0,\n          \"2\": \"0x0000000000000000000000000000000000000000000000000000000000000000\",\n          \"3\": \"0x04fbbea3bbc0804f05e823d23122858fa721df7e9c16993b81cb77a29a72693a073bebc00870477206be1b808070ab1abfb16ceabda9cb55d63b32e749b0b1bc03\",\n          \"4\": \"\",\n          \"requestID\": {\n            \"_hex\": \"0x02\"\n          },\n          \"level\": 0,\n          \"contentHash\": \"0x0000000000000000000000000000000000000000000000000000000000000000\",\n          \"pkeRequestor\": \"0x04fbbea3bbc0804f05e823d23122858fa721df7e9c16993b81cb77a29a72693a073bebc00870477206be1b808070ab1abfb16ceabda9cb55d63b32e749b0b1bc03\",\n          \"pkeAFGH\": \"\",\n          \"length\": 5\n        }\n      }\n    ],\n    \"blockNumber\": 756,\n    \"confirmations\": 1,\n    \"cumulativeGasUsed\": {\n      \"_hex\": \"0x1472b\"\n    },\n    \"status\": 1,\n    \"byzantium\": true\n  },\n  \"eventName\": \"AccessRequest\"\n});",
    "result": "{\n  \"name\": \"AccessRequest\",\n  \"signature\": \"AccessRequest(uint256,uint8,bytes32,string,string)\",\n  \"topic\": \"0x089a6f1788a3c353423e1be4ba12533bdde7d908bb41abeee185af0acb3df562\",\n  \"values\": {\n    \"0\": {\n      \"_hex\": \"0x02\"\n    },\n    \"1\": 0,\n    \"2\": \"0x0000000000000000000000000000000000000000000000000000000000000000\",\n    \"3\": \"0x04fbbea3bbc0804f05e823d23122858fa721df7e9c16993b81cb77a29a72693a073bebc00870477206be1b808070ab1abfb16ceabda9cb55d63b32e749b0b1bc03\",\n    \"4\": \"\",\n    \"requestID\": {\n      \"_hex\": \"0x02\"\n    },\n    \"level\": 0,\n    \"contentHash\": \"0x0000000000000000000000000000000000000000000000000000000000000000\",\n    \"pkeRequestor\": \"0x04fbbea3bbc0804f05e823d23122858fa721df7e9c16993b81cb77a29a72693a073bebc00870477206be1b808070ab1abfb16ceabda9cb55d63b32e749b0b1bc03\",\n    \"pkeAFGH\": \"\",\n    \"length\": 5\n  }\n}"
  },
  {
    "signature": "async ExtractEventFromLogs({\n  \"abi\": [\n    {\n      \"constant\": true,\n      \"inputs\": [],\n      \"name\": \"STATUS_PUBLISHED\",\n      \"outputs\": [\n        {\n          \"name\": \"\",\n          \"type\": \"bytes32\"\n        }\n      ],\n      \"payable\": false,\n      \"stateMutability\": \"view\",\n      \"type\": \"function\"\n    },\n    {\n      \"constant\": true,\n      \"inputs\": [],\n      \"name\": \"creator\",\n      \"outputs\": [\n        {\n          \"name\": \"\",\n          \"type\": \"address\"\n        }\n      ],\n      \"payable\": false,\n      \"stateMutability\": \"view\",\n      \"type\": \"function\"\n    },\n    {\n      \"constant\": false,\n      \"inputs\": [],\n      \"name\": \"publish\",\n      \"outputs\": [\n        {\n          \"name\": \"\",\n          \"type\": \"bool\"\n        }\n      ],\n      \"payable\": true,\n      \"stateMutability\": \"payable\",\n      \"type\": \"function\"\n    },\n    {\n      \"constant\": false,\n      \"inputs\": [\n        {\n          \"name\": \"request_ID\",\n          \"type\": \"uint256\"\n        },\n        {\n          \"name\": \"payee\",\n          \"type\": \"address\"\n        },\n        {\n          \"name\": \"label\",\n          \"type\": \"string\"\n        },\n        {\n          \"name\": \"amount\",\n          \"type\": \"uint256\"\n        }\n      ],\n      \"name\": \"processRequestPayment\",\n      \"outputs\": [\n        {\n          \"name\": \"\",\n          \"type\": \"bool\"\n        }\n      ],\n      \"payable\": false,\n      \"stateMutability\": \"nonpayable\",\n      \"type\": \"function\"\n    },\n    {\n      \"constant\": true,\n      \"inputs\": [\n        {\n          \"name\": \"\",\n          \"type\": \"uint256\"\n        }\n      ],\n      \"name\": \"requestMap\",\n      \"outputs\": [\n        {\n          \"name\": \"originator\",\n          \"type\": \"address\"\n        },\n        {\n          \"name\": \"amountPaid\",\n          \"type\": \"uint256\"\n        },\n        {\n          \"name\": \"status\",\n          \"type\": \"int8\"\n        },\n        {\n          \"name\": \"settled\",\n          \"type\": \"uint256\"\n        }\n      ],\n      \"payable\": false,\n      \"stateMutability\": \"view\",\n      \"type\": \"function\"\n    },\n    {\n      \"constant\": true,\n      \"inputs\": [],\n      \"name\": \"contentContractAddress\",\n      \"outputs\": [\n        {\n          \"name\": \"\",\n          \"type\": \"address\"\n        }\n      ],\n      \"payable\": false,\n      \"stateMutability\": \"view\",\n      \"type\": \"function\"\n    },\n    {\n      \"constant\": true,\n      \"inputs\": [],\n      \"name\": \"statusCode\",\n      \"outputs\": [\n        {\n          \"name\": \"\",\n          \"type\": \"int256\"\n        }\n      ],\n      \"payable\": false,\n      \"stateMutability\": \"view\",\n      \"type\": \"function\"\n    },\n    {\n      \"constant\": true,\n      \"inputs\": [],\n      \"name\": \"addressKMS\",\n      \"outputs\": [\n        {\n          \"name\": \"\",\n          \"type\": \"address\"\n        }\n      ],\n      \"payable\": false,\n      \"stateMutability\": \"view\",\n      \"type\": \"function\"\n    },\n    {\n      \"constant\": true,\n      \"inputs\": [],\n      \"name\": \"contentType\",\n      \"outputs\": [\n        {\n          \"name\": \"\",\n          \"type\": \"address\"\n        }\n      ],\n      \"payable\": false,\n      \"stateMutability\": \"view\",\n      \"type\": \"function\"\n    },\n    {\n      \"constant\": true,\n      \"inputs\": [\n        {\n          \"name\": \"status_code\",\n          \"type\": \"int256\"\n        }\n      ],\n      \"name\": \"statusCodeDescription\",\n      \"outputs\": [\n        {\n          \"name\": \"\",\n          \"type\": \"bytes32\"\n        }\n      ],\n      \"payable\": false,\n      \"stateMutability\": \"view\",\n      \"type\": \"function\"\n    },\n    {\n      \"constant\": true,\n      \"inputs\": [\n        {\n          \"name\": \"level\",\n          \"type\": \"uint8\"\n        },\n        {\n          \"name\": \"custom_values\",\n          \"type\": \"bytes32[]\"\n        },\n        {\n          \"name\": \"stakeholders\",\n          \"type\": \"address[]\"\n        }\n      ],\n      \"name\": \"getAccessInfo\",\n      \"outputs\": [\n        {\n          \"name\": \"\",\n          \"type\": \"int8\"\n        },\n        {\n          \"name\": \"\",\n          \"type\": \"uint256\"\n        }\n      ],\n      \"payable\": false,\n      \"stateMutability\": \"view\",\n      \"type\": \"function\"\n    },\n    {\n      \"constant\": false,\n      \"inputs\": [],\n      \"name\": \"kill\",\n      \"outputs\": [],\n      \"payable\": false,\n      \"stateMutability\": \"nonpayable\",\n      \"type\": \"function\"\n    },\n    {\n      \"constant\": true,\n      \"inputs\": [],\n      \"name\": \"STATUS_DRAFT\",\n      \"outputs\": [\n        {\n          \"name\": \"\",\n          \"type\": \"bytes32\"\n        }\n      ],\n      \"payable\": false,\n      \"stateMutability\": \"view\",\n      \"type\": \"function\"\n    },\n    {\n      \"constant\": false,\n      \"inputs\": [\n        {\n          \"name\": \"status_code\",\n          \"type\": \"int256\"\n        }\n      ],\n      \"name\": \"setStatusCode\",\n      \"outputs\": [\n        {\n          \"name\": \"\",\n          \"type\": \"int256\"\n        }\n      ],\n      \"payable\": false,\n      \"stateMutability\": \"nonpayable\",\n      \"type\": \"function\"\n    },\n    {\n      \"constant\": true,\n      \"inputs\": [],\n      \"name\": \"version\",\n      \"outputs\": [\n        {\n          \"name\": \"\",\n          \"type\": \"bytes32\"\n        }\n      ],\n      \"payable\": false,\n      \"stateMutability\": \"view\",\n      \"type\": \"function\"\n    },\n    {\n      \"constant\": false,\n      \"inputs\": [\n        {\n          \"name\": \"request_ID\",\n          \"type\": \"uint256\"\n        },\n        {\n          \"name\": \"score_pct\",\n          \"type\": \"uint256\"\n        },\n        {\n          \"name\": \"ml_out_hash\",\n          \"type\": \"bytes32\"\n        }\n      ],\n      \"name\": \"accessComplete\",\n      \"outputs\": [\n        {\n          \"name\": \"\",\n          \"type\": \"bool\"\n        }\n      ],\n      \"payable\": true,\n      \"stateMutability\": \"payable\",\n      \"type\": \"function\"\n    },\n    {\n      \"constant\": true,\n      \"inputs\": [],\n      \"name\": \"accessCharge\",\n      \"outputs\": [\n        {\n          \"name\": \"\",\n          \"type\": \"uint256\"\n        }\n      ],\n      \"payable\": false,\n      \"stateMutability\": \"view\",\n      \"type\": \"function\"\n    },\n    {\n      \"constant\": false,\n      \"inputs\": [\n        {\n          \"name\": \"newCreator\",\n          \"type\": \"address\"\n        }\n      ],\n      \"name\": \"transferCreatorship\",\n      \"outputs\": [],\n      \"payable\": false,\n      \"stateMutability\": \"nonpayable\",\n      \"type\": \"function\"\n    },\n    {\n      \"constant\": true,\n      \"inputs\": [\n        {\n          \"name\": \"\",\n          \"type\": \"uint256\"\n        }\n      ],\n      \"name\": \"versionHashes\",\n      \"outputs\": [\n        {\n          \"name\": \"\",\n          \"type\": \"bytes32\"\n        }\n      ],\n      \"payable\": false,\n      \"stateMutability\": \"view\",\n      \"type\": \"function\"\n    },\n    {\n      \"constant\": false,\n      \"inputs\": [\n        {\n          \"name\": \"status_code\",\n          \"type\": \"int256\"\n        }\n      ],\n      \"name\": \"updateStatus\",\n      \"outputs\": [\n        {\n          \"name\": \"\",\n          \"type\": \"int256\"\n        }\n      ],\n      \"payable\": false,\n      \"stateMutability\": \"nonpayable\",\n      \"type\": \"function\"\n    },\n    {\n      \"constant\": false,\n      \"inputs\": [\n        {\n          \"name\": \"level\",\n          \"type\": \"uint8\"\n        },\n        {\n          \"name\": \"custom_values\",\n          \"type\": \"bytes32[]\"\n        },\n        {\n          \"name\": \"stakeholders\",\n          \"type\": \"address[]\"\n        }\n      ],\n      \"name\": \"getAccessCharge\",\n      \"outputs\": [\n        {\n          \"name\": \"\",\n          \"type\": \"uint256\"\n        }\n      ],\n      \"payable\": false,\n      \"stateMutability\": \"nonpayable\",\n      \"type\": \"function\"\n    },\n    {\n      \"constant\": true,\n      \"inputs\": [],\n      \"name\": \"owner\",\n      \"outputs\": [\n        {\n          \"name\": \"\",\n          \"type\": \"address\"\n        }\n      ],\n      \"payable\": false,\n      \"stateMutability\": \"view\",\n      \"type\": \"function\"\n    },\n    {\n      \"constant\": true,\n      \"inputs\": [],\n      \"name\": \"requestID\",\n      \"outputs\": [\n        {\n          \"name\": \"\",\n          \"type\": \"uint256\"\n        }\n      ],\n      \"payable\": false,\n      \"stateMutability\": \"view\",\n      \"type\": \"function\"\n    },\n    {\n      \"constant\": false,\n      \"inputs\": [\n        {\n          \"name\": \"level\",\n          \"type\": \"uint8\"\n        },\n        {\n          \"name\": \"pke_requestor\",\n          \"type\": \"string\"\n        },\n        {\n          \"name\": \"pke_AFGH\",\n          \"type\": \"string\"\n        },\n        {\n          \"name\": \"custom_values\",\n          \"type\": \"bytes32[]\"\n        },\n        {\n          \"name\": \"stakeholders\",\n          \"type\": \"address[]\"\n        }\n      ],\n      \"name\": \"accessRequest\",\n      \"outputs\": [\n        {\n          \"name\": \"\",\n          \"type\": \"bool\"\n        }\n      ],\n      \"payable\": true,\n      \"stateMutability\": \"payable\",\n      \"type\": \"function\"\n    },\n    {\n      \"constant\": true,\n      \"inputs\": [],\n      \"name\": \"libraryAddress\",\n      \"outputs\": [\n        {\n          \"name\": \"\",\n          \"type\": \"address\"\n        }\n      ],\n      \"payable\": false,\n      \"stateMutability\": \"view\",\n      \"type\": \"function\"\n    },\n    {\n      \"constant\": false,\n      \"inputs\": [],\n      \"name\": \"updateRequest\",\n      \"outputs\": [],\n      \"payable\": false,\n      \"stateMutability\": \"nonpayable\",\n      \"type\": \"function\"\n    },\n    {\n      \"constant\": false,\n      \"inputs\": [\n        {\n          \"name\": \"address_KMS\",\n          \"type\": \"address\"\n        }\n      ],\n      \"name\": \"setAddressKMS\",\n      \"outputs\": [],\n      \"payable\": false,\n      \"stateMutability\": \"nonpayable\",\n      \"type\": \"function\"\n    },\n    {\n      \"constant\": true,\n      \"inputs\": [],\n      \"name\": \"canPublish\",\n      \"outputs\": [\n        {\n          \"name\": \"\",\n          \"type\": \"bool\"\n        }\n      ],\n      \"payable\": false,\n      \"stateMutability\": \"view\",\n      \"type\": \"function\"\n    },\n    {\n      \"constant\": true,\n      \"inputs\": [],\n      \"name\": \"STATUS_REVIEW\",\n      \"outputs\": [\n        {\n          \"name\": \"\",\n          \"type\": \"bytes32\"\n        }\n      ],\n      \"payable\": false,\n      \"stateMutability\": \"view\",\n      \"type\": \"function\"\n    },\n    {\n      \"constant\": true,\n      \"inputs\": [],\n      \"name\": \"objectHash\",\n      \"outputs\": [\n        {\n          \"name\": \"\",\n          \"type\": \"bytes32\"\n        }\n      ],\n      \"payable\": false,\n      \"stateMutability\": \"view\",\n      \"type\": \"function\"\n    },\n    {\n      \"constant\": false,\n      \"inputs\": [\n        {\n          \"name\": \"addr\",\n          \"type\": \"address\"\n        }\n      ],\n      \"name\": \"setContentContractAddress\",\n      \"outputs\": [],\n      \"payable\": false,\n      \"stateMutability\": \"nonpayable\",\n      \"type\": \"function\"\n    },\n    {\n      \"constant\": false,\n      \"inputs\": [\n        {\n          \"name\": \"request_ID\",\n          \"type\": \"uint256\"\n        },\n        {\n          \"name\": \"access_granted\",\n          \"type\": \"bool\"\n        },\n        {\n          \"name\": \"re_key\",\n          \"type\": \"string\"\n        },\n        {\n          \"name\": \"encrypted_AES_key\",\n          \"type\": \"string\"\n        }\n      ],\n      \"name\": \"accessGrant\",\n      \"outputs\": [\n        {\n          \"name\": \"\",\n          \"type\": \"bool\"\n        }\n      ],\n      \"payable\": false,\n      \"stateMutability\": \"nonpayable\",\n      \"type\": \"function\"\n    },\n    {\n      \"constant\": false,\n      \"inputs\": [\n        {\n          \"name\": \"_objectHash\",\n          \"type\": \"bytes32\"\n        }\n      ],\n      \"name\": \"commit\",\n      \"outputs\": [],\n      \"payable\": false,\n      \"stateMutability\": \"nonpayable\",\n      \"type\": \"function\"\n    },\n    {\n      \"constant\": false,\n      \"inputs\": [\n        {\n          \"name\": \"newOwner\",\n          \"type\": \"address\"\n        }\n      ],\n      \"name\": \"transferOwnership\",\n      \"outputs\": [],\n      \"payable\": false,\n      \"stateMutability\": \"nonpayable\",\n      \"type\": \"function\"\n    },\n    {\n      \"constant\": false,\n      \"inputs\": [\n        {\n          \"name\": \"charge\",\n          \"type\": \"uint256\"\n        }\n      ],\n      \"name\": \"setAccessCharge\",\n      \"outputs\": [\n        {\n          \"name\": \"\",\n          \"type\": \"uint256\"\n        }\n      ],\n      \"payable\": false,\n      \"stateMutability\": \"nonpayable\",\n      \"type\": \"function\"\n    },\n    {\n      \"constant\": true,\n      \"inputs\": [],\n      \"name\": \"statusDescription\",\n      \"outputs\": [\n        {\n          \"name\": \"\",\n          \"type\": \"bytes32\"\n        }\n      ],\n      \"payable\": false,\n      \"stateMutability\": \"view\",\n      \"type\": \"function\"\n    },\n    {\n      \"inputs\": [\n        {\n          \"name\": \"content_type\",\n          \"type\": \"address\"\n        }\n      ],\n      \"payable\": true,\n      \"stateMutability\": \"payable\",\n      \"type\": \"constructor\"\n    },\n    {\n      \"payable\": true,\n      \"stateMutability\": \"payable\",\n      \"type\": \"fallback\"\n    },\n    {\n      \"anonymous\": false,\n      \"inputs\": [\n        {\n          \"indexed\": false,\n          \"name\": \"containingLibrary\",\n          \"type\": \"address\"\n        }\n      ],\n      \"name\": \"ContentObjectCreate\",\n      \"type\": \"event\"\n    },\n    {\n      \"anonymous\": false,\n      \"inputs\": [\n        {\n          \"indexed\": false,\n          \"name\": \"contentType\",\n          \"type\": \"address\"\n        },\n        {\n          \"indexed\": false,\n          \"name\": \"contentContractAddress\",\n          \"type\": \"address\"\n        }\n      ],\n      \"name\": \"SetContentType\",\n      \"type\": \"event\"\n    },\n    {\n      \"anonymous\": false,\n      \"inputs\": [\n        {\n          \"indexed\": false,\n          \"name\": \"requestID\",\n          \"type\": \"uint256\"\n        },\n        {\n          \"indexed\": false,\n          \"name\": \"level\",\n          \"type\": \"uint8\"\n        },\n        {\n          \"indexed\": false,\n          \"name\": \"contentHash\",\n          \"type\": \"bytes32\"\n        },\n        {\n          \"indexed\": false,\n          \"name\": \"pkeRequestor\",\n          \"type\": \"string\"\n        },\n        {\n          \"indexed\": false,\n          \"name\": \"pkeAFGH\",\n          \"type\": \"string\"\n        }\n      ],\n      \"name\": \"AccessRequest\",\n      \"type\": \"event\"\n    },\n    {\n      \"anonymous\": false,\n      \"inputs\": [\n        {\n          \"indexed\": false,\n          \"name\": \"requestID\",\n          \"type\": \"uint256\"\n        },\n        {\n          \"indexed\": false,\n          \"name\": \"label\",\n          \"type\": \"string\"\n        },\n        {\n          \"indexed\": false,\n          \"name\": \"payee\",\n          \"type\": \"address\"\n        },\n        {\n          \"indexed\": false,\n          \"name\": \"amount\",\n          \"type\": \"uint256\"\n        }\n      ],\n      \"name\": \"LogPayment\",\n      \"type\": \"event\"\n    },\n    {\n      \"anonymous\": false,\n      \"inputs\": [\n        {\n          \"indexed\": false,\n          \"name\": \"requestID\",\n          \"type\": \"uint256\"\n        },\n        {\n          \"indexed\": false,\n          \"name\": \"access_granted\",\n          \"type\": \"bool\"\n        },\n        {\n          \"indexed\": false,\n          \"name\": \"reKey\",\n          \"type\": \"string\"\n        },\n        {\n          \"indexed\": false,\n          \"name\": \"encryptedAESKey\",\n          \"type\": \"string\"\n        }\n      ],\n      \"name\": \"AccessGrant\",\n      \"type\": \"event\"\n    },\n    {\n      \"anonymous\": false,\n      \"inputs\": [\n        {\n          \"indexed\": false,\n          \"name\": \"customValue\",\n          \"type\": \"bytes32\"\n        }\n      ],\n      \"name\": \"AccessRequestValue\",\n      \"type\": \"event\"\n    },\n    {\n      \"anonymous\": false,\n      \"inputs\": [\n        {\n          \"indexed\": false,\n          \"name\": \"stakeholder\",\n          \"type\": \"address\"\n        }\n      ],\n      \"name\": \"AccessRequestStakeholder\",\n      \"type\": \"event\"\n    },\n    {\n      \"anonymous\": false,\n      \"inputs\": [\n        {\n          \"indexed\": false,\n          \"name\": \"requestID\",\n          \"type\": \"uint256\"\n        },\n        {\n          \"indexed\": false,\n          \"name\": \"scorePct\",\n          \"type\": \"uint256\"\n        },\n        {\n          \"indexed\": false,\n          \"name\": \"mlOutHash\",\n          \"type\": \"bytes32\"\n        },\n        {\n          \"indexed\": false,\n          \"name\": \"customContractResult\",\n          \"type\": \"bool\"\n        }\n      ],\n      \"name\": \"AccessComplete\",\n      \"type\": \"event\"\n    },\n    {\n      \"anonymous\": false,\n      \"inputs\": [\n        {\n          \"indexed\": false,\n          \"name\": \"contentContractAddress\",\n          \"type\": \"address\"\n        }\n      ],\n      \"name\": \"SetContentContract\",\n      \"type\": \"event\"\n    },\n    {\n      \"anonymous\": false,\n      \"inputs\": [\n        {\n          \"indexed\": false,\n          \"name\": \"accessCharge\",\n          \"type\": \"uint256\"\n        }\n      ],\n      \"name\": \"SetAccessCharge\",\n      \"type\": \"event\"\n    },\n    {\n      \"anonymous\": false,\n      \"inputs\": [\n        {\n          \"indexed\": false,\n          \"name\": \"level\",\n          \"type\": \"uint8\"\n        },\n        {\n          \"indexed\": false,\n          \"name\": \"accessCharge\",\n          \"type\": \"uint256\"\n        }\n      ],\n      \"name\": \"GetAccessCharge\",\n      \"type\": \"event\"\n    },\n    {\n      \"anonymous\": false,\n      \"inputs\": [\n        {\n          \"indexed\": false,\n          \"name\": \"accessCharge\",\n          \"type\": \"uint256\"\n        },\n        {\n          \"indexed\": false,\n          \"name\": \"amountProvided\",\n          \"type\": \"uint256\"\n        }\n      ],\n      \"name\": \"InsufficientFunds\",\n      \"type\": \"event\"\n    },\n    {\n      \"anonymous\": false,\n      \"inputs\": [\n        {\n          \"indexed\": false,\n          \"name\": \"statusCode\",\n          \"type\": \"int256\"\n        }\n      ],\n      \"name\": \"SetStatusCode\",\n      \"type\": \"event\"\n    },\n    {\n      \"anonymous\": false,\n      \"inputs\": [\n        {\n          \"indexed\": false,\n          \"name\": \"requestStatus\",\n          \"type\": \"bool\"\n        },\n        {\n          \"indexed\": false,\n          \"name\": \"statusCode\",\n          \"type\": \"int256\"\n        },\n        {\n          \"indexed\": false,\n          \"name\": \"objectHash\",\n          \"type\": \"bytes32\"\n        }\n      ],\n      \"name\": \"Publish\",\n      \"type\": \"event\"\n    },\n    {\n      \"anonymous\": false,\n      \"inputs\": [\n        {\n          \"indexed\": false,\n          \"name\": \"custom_contract\",\n          \"type\": \"address\"\n        }\n      ],\n      \"name\": \"InvokeCustomPreHook\",\n      \"type\": \"event\"\n    },\n    {\n      \"anonymous\": false,\n      \"inputs\": [\n        {\n          \"indexed\": false,\n          \"name\": \"custom_contract\",\n          \"type\": \"address\"\n        },\n        {\n          \"indexed\": false,\n          \"name\": \"result\",\n          \"type\": \"uint256\"\n        }\n      ],\n      \"name\": \"ReturnCustomHook\",\n      \"type\": \"event\"\n    },\n    {\n      \"anonymous\": false,\n      \"inputs\": [\n        {\n          \"indexed\": false,\n          \"name\": \"custom_contract\",\n          \"type\": \"address\"\n        }\n      ],\n      \"name\": \"InvokeCustomPostHook\",\n      \"type\": \"event\"\n    },\n    {\n      \"anonymous\": false,\n      \"inputs\": [\n        {\n          \"indexed\": false,\n          \"name\": \"objectHash\",\n          \"type\": \"bytes32\"\n        }\n      ],\n      \"name\": \"CommitPending\",\n      \"type\": \"event\"\n    },\n    {\n      \"anonymous\": false,\n      \"inputs\": [\n        {\n          \"indexed\": false,\n          \"name\": \"objectHash\",\n          \"type\": \"bytes32\"\n        }\n      ],\n      \"name\": \"Commit\",\n      \"type\": \"event\"\n    },\n    {\n      \"anonymous\": false,\n      \"inputs\": [\n        {\n          \"indexed\": false,\n          \"name\": \"objectHash\",\n          \"type\": \"bytes32\"\n        }\n      ],\n      \"name\": \"UpdateRequest\",\n      \"type\": \"event\"\n    }\n  ],\n  \"event\": {\n    \"to\": \"0x61E76Bc8b01352A2b12d8e8949F9c1CDF6ca447D\",\n    \"from\": \"0xc2635Ab30Fc19F616332c6d2d7F14cdAf7ce1965\",\n    \"contractAddress\": null,\n    \"transactionIndex\": 0,\n    \"gasUsed\": {\n      \"_hex\": \"0x1838d\"\n    },\n    \"logsBloom\": \"0x00000000040000000000000000040000000000000000000000000000000000000000080000000000000000000000000000000000000000000000000000000000080000000000000000000000000000000000000000000000000000000000000000000000000000000000000000000000000000000000000000000000000000000000000000000000000000010000000000000000000000000001000000000000000000000000000000000000000000000000000000000000000000000000000000000000000000000000000000000000000000000000000000000000000000000000000000000000000000000000000000000000000000000000000000000000\",\n    \"blockHash\": \"0x1899856f8543d30e6a3180b2b61d018d55254b9757a4b87416381e15d07e901f\",\n    \"transactionHash\": \"0x311b46a06c5802b405f5575bb537f3a8b48cfcdd6ded1f64cbc0cac9a1aaf5f4\",\n    \"logs\": [\n      {\n        \"transactionIndex\": 0,\n        \"blockNumber\": 759,\n        \"transactionHash\": \"0x311b46a06c5802b405f5575bb537f3a8b48cfcdd6ded1f64cbc0cac9a1aaf5f4\",\n        \"address\": \"0x61E76Bc8b01352A2b12d8e8949F9c1CDF6ca447D\",\n        \"topics\": [\n          \"0xa6f2e38f0cfebf27212317fced3ac40bc62e00bd33f38d69603710740c69acb7\"\n        ],\n        \"data\": \"0x0000000000000000000000007f7f7d26bb598a2e485ffb9b1486c37b34fd242a\",\n        \"logIndex\": 0,\n        \"blockHash\": \"0x1899856f8543d30e6a3180b2b61d018d55254b9757a4b87416381e15d07e901f\",\n        \"transactionLogIndex\": 0,\n        \"name\": \"SetContentContract\",\n        \"signature\": \"SetContentContract(address)\",\n        \"topic\": \"0xa6f2e38f0cfebf27212317fced3ac40bc62e00bd33f38d69603710740c69acb7\",\n        \"values\": {\n          \"0\": \"0x7F7f7D26BB598A2E485FFB9b1486c37b34fD242A\",\n          \"contentContractAddress\": \"0x7F7f7D26BB598A2E485FFB9b1486c37b34fD242A\",\n          \"length\": 1\n        }\n      }\n    ],\n    \"blockNumber\": 759,\n    \"confirmations\": 1,\n    \"cumulativeGasUsed\": {\n      \"_hex\": \"0x1838d\"\n    },\n    \"status\": 1,\n    \"byzantium\": true\n  },\n  \"eventName\": \"SetContentContract\"\n});",
    "result": "{\n  \"name\": \"SetContentContract\",\n  \"signature\": \"SetContentContract(address)\",\n  \"topic\": \"0xa6f2e38f0cfebf27212317fced3ac40bc62e00bd33f38d69603710740c69acb7\",\n  \"values\": {\n    \"0\": \"0x7F7f7D26BB598A2E485FFB9b1486c37b34fD242A\",\n    \"contentContractAddress\": \"0x7F7f7D26BB598A2E485FFB9b1486c37b34fD242A\",\n    \"length\": 1\n  }\n}"
  },
  {
    "signature": "async ExtractEventFromLogs({\n  \"abi\": [\n    {\n      \"constant\": true,\n      \"inputs\": [],\n      \"name\": \"STATUS_PUBLISHED\",\n      \"outputs\": [\n        {\n          \"name\": \"\",\n          \"type\": \"bytes32\"\n        }\n      ],\n      \"payable\": false,\n      \"stateMutability\": \"view\",\n      \"type\": \"function\"\n    },\n    {\n      \"constant\": true,\n      \"inputs\": [],\n      \"name\": \"creator\",\n      \"outputs\": [\n        {\n          \"name\": \"\",\n          \"type\": \"address\"\n        }\n      ],\n      \"payable\": false,\n      \"stateMutability\": \"view\",\n      \"type\": \"function\"\n    },\n    {\n      \"constant\": false,\n      \"inputs\": [],\n      \"name\": \"publish\",\n      \"outputs\": [\n        {\n          \"name\": \"\",\n          \"type\": \"bool\"\n        }\n      ],\n      \"payable\": true,\n      \"stateMutability\": \"payable\",\n      \"type\": \"function\"\n    },\n    {\n      \"constant\": false,\n      \"inputs\": [\n        {\n          \"name\": \"request_ID\",\n          \"type\": \"uint256\"\n        },\n        {\n          \"name\": \"payee\",\n          \"type\": \"address\"\n        },\n        {\n          \"name\": \"label\",\n          \"type\": \"string\"\n        },\n        {\n          \"name\": \"amount\",\n          \"type\": \"uint256\"\n        }\n      ],\n      \"name\": \"processRequestPayment\",\n      \"outputs\": [\n        {\n          \"name\": \"\",\n          \"type\": \"bool\"\n        }\n      ],\n      \"payable\": false,\n      \"stateMutability\": \"nonpayable\",\n      \"type\": \"function\"\n    },\n    {\n      \"constant\": true,\n      \"inputs\": [\n        {\n          \"name\": \"\",\n          \"type\": \"uint256\"\n        }\n      ],\n      \"name\": \"requestMap\",\n      \"outputs\": [\n        {\n          \"name\": \"originator\",\n          \"type\": \"address\"\n        },\n        {\n          \"name\": \"amountPaid\",\n          \"type\": \"uint256\"\n        },\n        {\n          \"name\": \"status\",\n          \"type\": \"int8\"\n        },\n        {\n          \"name\": \"settled\",\n          \"type\": \"uint256\"\n        }\n      ],\n      \"payable\": false,\n      \"stateMutability\": \"view\",\n      \"type\": \"function\"\n    },\n    {\n      \"constant\": true,\n      \"inputs\": [],\n      \"name\": \"contentContractAddress\",\n      \"outputs\": [\n        {\n          \"name\": \"\",\n          \"type\": \"address\"\n        }\n      ],\n      \"payable\": false,\n      \"stateMutability\": \"view\",\n      \"type\": \"function\"\n    },\n    {\n      \"constant\": true,\n      \"inputs\": [],\n      \"name\": \"statusCode\",\n      \"outputs\": [\n        {\n          \"name\": \"\",\n          \"type\": \"int256\"\n        }\n      ],\n      \"payable\": false,\n      \"stateMutability\": \"view\",\n      \"type\": \"function\"\n    },\n    {\n      \"constant\": true,\n      \"inputs\": [],\n      \"name\": \"addressKMS\",\n      \"outputs\": [\n        {\n          \"name\": \"\",\n          \"type\": \"address\"\n        }\n      ],\n      \"payable\": false,\n      \"stateMutability\": \"view\",\n      \"type\": \"function\"\n    },\n    {\n      \"constant\": true,\n      \"inputs\": [],\n      \"name\": \"contentType\",\n      \"outputs\": [\n        {\n          \"name\": \"\",\n          \"type\": \"address\"\n        }\n      ],\n      \"payable\": false,\n      \"stateMutability\": \"view\",\n      \"type\": \"function\"\n    },\n    {\n      \"constant\": true,\n      \"inputs\": [\n        {\n          \"name\": \"status_code\",\n          \"type\": \"int256\"\n        }\n      ],\n      \"name\": \"statusCodeDescription\",\n      \"outputs\": [\n        {\n          \"name\": \"\",\n          \"type\": \"bytes32\"\n        }\n      ],\n      \"payable\": false,\n      \"stateMutability\": \"view\",\n      \"type\": \"function\"\n    },\n    {\n      \"constant\": true,\n      \"inputs\": [\n        {\n          \"name\": \"level\",\n          \"type\": \"uint8\"\n        },\n        {\n          \"name\": \"custom_values\",\n          \"type\": \"bytes32[]\"\n        },\n        {\n          \"name\": \"stakeholders\",\n          \"type\": \"address[]\"\n        }\n      ],\n      \"name\": \"getAccessInfo\",\n      \"outputs\": [\n        {\n          \"name\": \"\",\n          \"type\": \"int8\"\n        },\n        {\n          \"name\": \"\",\n          \"type\": \"uint256\"\n        }\n      ],\n      \"payable\": false,\n      \"stateMutability\": \"view\",\n      \"type\": \"function\"\n    },\n    {\n      \"constant\": false,\n      \"inputs\": [],\n      \"name\": \"kill\",\n      \"outputs\": [],\n      \"payable\": false,\n      \"stateMutability\": \"nonpayable\",\n      \"type\": \"function\"\n    },\n    {\n      \"constant\": true,\n      \"inputs\": [],\n      \"name\": \"STATUS_DRAFT\",\n      \"outputs\": [\n        {\n          \"name\": \"\",\n          \"type\": \"bytes32\"\n        }\n      ],\n      \"payable\": false,\n      \"stateMutability\": \"view\",\n      \"type\": \"function\"\n    },\n    {\n      \"constant\": false,\n      \"inputs\": [\n        {\n          \"name\": \"status_code\",\n          \"type\": \"int256\"\n        }\n      ],\n      \"name\": \"setStatusCode\",\n      \"outputs\": [\n        {\n          \"name\": \"\",\n          \"type\": \"int256\"\n        }\n      ],\n      \"payable\": false,\n      \"stateMutability\": \"nonpayable\",\n      \"type\": \"function\"\n    },\n    {\n      \"constant\": true,\n      \"inputs\": [],\n      \"name\": \"version\",\n      \"outputs\": [\n        {\n          \"name\": \"\",\n          \"type\": \"bytes32\"\n        }\n      ],\n      \"payable\": false,\n      \"stateMutability\": \"view\",\n      \"type\": \"function\"\n    },\n    {\n      \"constant\": false,\n      \"inputs\": [\n        {\n          \"name\": \"request_ID\",\n          \"type\": \"uint256\"\n        },\n        {\n          \"name\": \"score_pct\",\n          \"type\": \"uint256\"\n        },\n        {\n          \"name\": \"ml_out_hash\",\n          \"type\": \"bytes32\"\n        }\n      ],\n      \"name\": \"accessComplete\",\n      \"outputs\": [\n        {\n          \"name\": \"\",\n          \"type\": \"bool\"\n        }\n      ],\n      \"payable\": true,\n      \"stateMutability\": \"payable\",\n      \"type\": \"function\"\n    },\n    {\n      \"constant\": true,\n      \"inputs\": [],\n      \"name\": \"accessCharge\",\n      \"outputs\": [\n        {\n          \"name\": \"\",\n          \"type\": \"uint256\"\n        }\n      ],\n      \"payable\": false,\n      \"stateMutability\": \"view\",\n      \"type\": \"function\"\n    },\n    {\n      \"constant\": false,\n      \"inputs\": [\n        {\n          \"name\": \"newCreator\",\n          \"type\": \"address\"\n        }\n      ],\n      \"name\": \"transferCreatorship\",\n      \"outputs\": [],\n      \"payable\": false,\n      \"stateMutability\": \"nonpayable\",\n      \"type\": \"function\"\n    },\n    {\n      \"constant\": true,\n      \"inputs\": [\n        {\n          \"name\": \"\",\n          \"type\": \"uint256\"\n        }\n      ],\n      \"name\": \"versionHashes\",\n      \"outputs\": [\n        {\n          \"name\": \"\",\n          \"type\": \"bytes32\"\n        }\n      ],\n      \"payable\": false,\n      \"stateMutability\": \"view\",\n      \"type\": \"function\"\n    },\n    {\n      \"constant\": false,\n      \"inputs\": [\n        {\n          \"name\": \"status_code\",\n          \"type\": \"int256\"\n        }\n      ],\n      \"name\": \"updateStatus\",\n      \"outputs\": [\n        {\n          \"name\": \"\",\n          \"type\": \"int256\"\n        }\n      ],\n      \"payable\": false,\n      \"stateMutability\": \"nonpayable\",\n      \"type\": \"function\"\n    },\n    {\n      \"constant\": false,\n      \"inputs\": [\n        {\n          \"name\": \"level\",\n          \"type\": \"uint8\"\n        },\n        {\n          \"name\": \"custom_values\",\n          \"type\": \"bytes32[]\"\n        },\n        {\n          \"name\": \"stakeholders\",\n          \"type\": \"address[]\"\n        }\n      ],\n      \"name\": \"getAccessCharge\",\n      \"outputs\": [\n        {\n          \"name\": \"\",\n          \"type\": \"uint256\"\n        }\n      ],\n      \"payable\": false,\n      \"stateMutability\": \"nonpayable\",\n      \"type\": \"function\"\n    },\n    {\n      \"constant\": true,\n      \"inputs\": [],\n      \"name\": \"owner\",\n      \"outputs\": [\n        {\n          \"name\": \"\",\n          \"type\": \"address\"\n        }\n      ],\n      \"payable\": false,\n      \"stateMutability\": \"view\",\n      \"type\": \"function\"\n    },\n    {\n      \"constant\": true,\n      \"inputs\": [],\n      \"name\": \"requestID\",\n      \"outputs\": [\n        {\n          \"name\": \"\",\n          \"type\": \"uint256\"\n        }\n      ],\n      \"payable\": false,\n      \"stateMutability\": \"view\",\n      \"type\": \"function\"\n    },\n    {\n      \"constant\": false,\n      \"inputs\": [\n        {\n          \"name\": \"level\",\n          \"type\": \"uint8\"\n        },\n        {\n          \"name\": \"pke_requestor\",\n          \"type\": \"string\"\n        },\n        {\n          \"name\": \"pke_AFGH\",\n          \"type\": \"string\"\n        },\n        {\n          \"name\": \"custom_values\",\n          \"type\": \"bytes32[]\"\n        },\n        {\n          \"name\": \"stakeholders\",\n          \"type\": \"address[]\"\n        }\n      ],\n      \"name\": \"accessRequest\",\n      \"outputs\": [\n        {\n          \"name\": \"\",\n          \"type\": \"bool\"\n        }\n      ],\n      \"payable\": true,\n      \"stateMutability\": \"payable\",\n      \"type\": \"function\"\n    },\n    {\n      \"constant\": true,\n      \"inputs\": [],\n      \"name\": \"libraryAddress\",\n      \"outputs\": [\n        {\n          \"name\": \"\",\n          \"type\": \"address\"\n        }\n      ],\n      \"payable\": false,\n      \"stateMutability\": \"view\",\n      \"type\": \"function\"\n    },\n    {\n      \"constant\": false,\n      \"inputs\": [],\n      \"name\": \"updateRequest\",\n      \"outputs\": [],\n      \"payable\": false,\n      \"stateMutability\": \"nonpayable\",\n      \"type\": \"function\"\n    },\n    {\n      \"constant\": false,\n      \"inputs\": [\n        {\n          \"name\": \"address_KMS\",\n          \"type\": \"address\"\n        }\n      ],\n      \"name\": \"setAddressKMS\",\n      \"outputs\": [],\n      \"payable\": false,\n      \"stateMutability\": \"nonpayable\",\n      \"type\": \"function\"\n    },\n    {\n      \"constant\": true,\n      \"inputs\": [],\n      \"name\": \"canPublish\",\n      \"outputs\": [\n        {\n          \"name\": \"\",\n          \"type\": \"bool\"\n        }\n      ],\n      \"payable\": false,\n      \"stateMutability\": \"view\",\n      \"type\": \"function\"\n    },\n    {\n      \"constant\": true,\n      \"inputs\": [],\n      \"name\": \"STATUS_REVIEW\",\n      \"outputs\": [\n        {\n          \"name\": \"\",\n          \"type\": \"bytes32\"\n        }\n      ],\n      \"payable\": false,\n      \"stateMutability\": \"view\",\n      \"type\": \"function\"\n    },\n    {\n      \"constant\": true,\n      \"inputs\": [],\n      \"name\": \"objectHash\",\n      \"outputs\": [\n        {\n          \"name\": \"\",\n          \"type\": \"bytes32\"\n        }\n      ],\n      \"payable\": false,\n      \"stateMutability\": \"view\",\n      \"type\": \"function\"\n    },\n    {\n      \"constant\": false,\n      \"inputs\": [\n        {\n          \"name\": \"addr\",\n          \"type\": \"address\"\n        }\n      ],\n      \"name\": \"setContentContractAddress\",\n      \"outputs\": [],\n      \"payable\": false,\n      \"stateMutability\": \"nonpayable\",\n      \"type\": \"function\"\n    },\n    {\n      \"constant\": false,\n      \"inputs\": [\n        {\n          \"name\": \"request_ID\",\n          \"type\": \"uint256\"\n        },\n        {\n          \"name\": \"access_granted\",\n          \"type\": \"bool\"\n        },\n        {\n          \"name\": \"re_key\",\n          \"type\": \"string\"\n        },\n        {\n          \"name\": \"encrypted_AES_key\",\n          \"type\": \"string\"\n        }\n      ],\n      \"name\": \"accessGrant\",\n      \"outputs\": [\n        {\n          \"name\": \"\",\n          \"type\": \"bool\"\n        }\n      ],\n      \"payable\": false,\n      \"stateMutability\": \"nonpayable\",\n      \"type\": \"function\"\n    },\n    {\n      \"constant\": false,\n      \"inputs\": [\n        {\n          \"name\": \"_objectHash\",\n          \"type\": \"bytes32\"\n        }\n      ],\n      \"name\": \"commit\",\n      \"outputs\": [],\n      \"payable\": false,\n      \"stateMutability\": \"nonpayable\",\n      \"type\": \"function\"\n    },\n    {\n      \"constant\": false,\n      \"inputs\": [\n        {\n          \"name\": \"newOwner\",\n          \"type\": \"address\"\n        }\n      ],\n      \"name\": \"transferOwnership\",\n      \"outputs\": [],\n      \"payable\": false,\n      \"stateMutability\": \"nonpayable\",\n      \"type\": \"function\"\n    },\n    {\n      \"constant\": false,\n      \"inputs\": [\n        {\n          \"name\": \"charge\",\n          \"type\": \"uint256\"\n        }\n      ],\n      \"name\": \"setAccessCharge\",\n      \"outputs\": [\n        {\n          \"name\": \"\",\n          \"type\": \"uint256\"\n        }\n      ],\n      \"payable\": false,\n      \"stateMutability\": \"nonpayable\",\n      \"type\": \"function\"\n    },\n    {\n      \"constant\": true,\n      \"inputs\": [],\n      \"name\": \"statusDescription\",\n      \"outputs\": [\n        {\n          \"name\": \"\",\n          \"type\": \"bytes32\"\n        }\n      ],\n      \"payable\": false,\n      \"stateMutability\": \"view\",\n      \"type\": \"function\"\n    },\n    {\n      \"inputs\": [\n        {\n          \"name\": \"content_type\",\n          \"type\": \"address\"\n        }\n      ],\n      \"payable\": true,\n      \"stateMutability\": \"payable\",\n      \"type\": \"constructor\"\n    },\n    {\n      \"payable\": true,\n      \"stateMutability\": \"payable\",\n      \"type\": \"fallback\"\n    },\n    {\n      \"anonymous\": false,\n      \"inputs\": [\n        {\n          \"indexed\": false,\n          \"name\": \"containingLibrary\",\n          \"type\": \"address\"\n        }\n      ],\n      \"name\": \"ContentObjectCreate\",\n      \"type\": \"event\"\n    },\n    {\n      \"anonymous\": false,\n      \"inputs\": [\n        {\n          \"indexed\": false,\n          \"name\": \"contentType\",\n          \"type\": \"address\"\n        },\n        {\n          \"indexed\": false,\n          \"name\": \"contentContractAddress\",\n          \"type\": \"address\"\n        }\n      ],\n      \"name\": \"SetContentType\",\n      \"type\": \"event\"\n    },\n    {\n      \"anonymous\": false,\n      \"inputs\": [\n        {\n          \"indexed\": false,\n          \"name\": \"requestID\",\n          \"type\": \"uint256\"\n        },\n        {\n          \"indexed\": false,\n          \"name\": \"level\",\n          \"type\": \"uint8\"\n        },\n        {\n          \"indexed\": false,\n          \"name\": \"contentHash\",\n          \"type\": \"bytes32\"\n        },\n        {\n          \"indexed\": false,\n          \"name\": \"pkeRequestor\",\n          \"type\": \"string\"\n        },\n        {\n          \"indexed\": false,\n          \"name\": \"pkeAFGH\",\n          \"type\": \"string\"\n        }\n      ],\n      \"name\": \"AccessRequest\",\n      \"type\": \"event\"\n    },\n    {\n      \"anonymous\": false,\n      \"inputs\": [\n        {\n          \"indexed\": false,\n          \"name\": \"requestID\",\n          \"type\": \"uint256\"\n        },\n        {\n          \"indexed\": false,\n          \"name\": \"label\",\n          \"type\": \"string\"\n        },\n        {\n          \"indexed\": false,\n          \"name\": \"payee\",\n          \"type\": \"address\"\n        },\n        {\n          \"indexed\": false,\n          \"name\": \"amount\",\n          \"type\": \"uint256\"\n        }\n      ],\n      \"name\": \"LogPayment\",\n      \"type\": \"event\"\n    },\n    {\n      \"anonymous\": false,\n      \"inputs\": [\n        {\n          \"indexed\": false,\n          \"name\": \"requestID\",\n          \"type\": \"uint256\"\n        },\n        {\n          \"indexed\": false,\n          \"name\": \"access_granted\",\n          \"type\": \"bool\"\n        },\n        {\n          \"indexed\": false,\n          \"name\": \"reKey\",\n          \"type\": \"string\"\n        },\n        {\n          \"indexed\": false,\n          \"name\": \"encryptedAESKey\",\n          \"type\": \"string\"\n        }\n      ],\n      \"name\": \"AccessGrant\",\n      \"type\": \"event\"\n    },\n    {\n      \"anonymous\": false,\n      \"inputs\": [\n        {\n          \"indexed\": false,\n          \"name\": \"customValue\",\n          \"type\": \"bytes32\"\n        }\n      ],\n      \"name\": \"AccessRequestValue\",\n      \"type\": \"event\"\n    },\n    {\n      \"anonymous\": false,\n      \"inputs\": [\n        {\n          \"indexed\": false,\n          \"name\": \"stakeholder\",\n          \"type\": \"address\"\n        }\n      ],\n      \"name\": \"AccessRequestStakeholder\",\n      \"type\": \"event\"\n    },\n    {\n      \"anonymous\": false,\n      \"inputs\": [\n        {\n          \"indexed\": false,\n          \"name\": \"requestID\",\n          \"type\": \"uint256\"\n        },\n        {\n          \"indexed\": false,\n          \"name\": \"scorePct\",\n          \"type\": \"uint256\"\n        },\n        {\n          \"indexed\": false,\n          \"name\": \"mlOutHash\",\n          \"type\": \"bytes32\"\n        },\n        {\n          \"indexed\": false,\n          \"name\": \"customContractResult\",\n          \"type\": \"bool\"\n        }\n      ],\n      \"name\": \"AccessComplete\",\n      \"type\": \"event\"\n    },\n    {\n      \"anonymous\": false,\n      \"inputs\": [\n        {\n          \"indexed\": false,\n          \"name\": \"contentContractAddress\",\n          \"type\": \"address\"\n        }\n      ],\n      \"name\": \"SetContentContract\",\n      \"type\": \"event\"\n    },\n    {\n      \"anonymous\": false,\n      \"inputs\": [\n        {\n          \"indexed\": false,\n          \"name\": \"accessCharge\",\n          \"type\": \"uint256\"\n        }\n      ],\n      \"name\": \"SetAccessCharge\",\n      \"type\": \"event\"\n    },\n    {\n      \"anonymous\": false,\n      \"inputs\": [\n        {\n          \"indexed\": false,\n          \"name\": \"level\",\n          \"type\": \"uint8\"\n        },\n        {\n          \"indexed\": false,\n          \"name\": \"accessCharge\",\n          \"type\": \"uint256\"\n        }\n      ],\n      \"name\": \"GetAccessCharge\",\n      \"type\": \"event\"\n    },\n    {\n      \"anonymous\": false,\n      \"inputs\": [\n        {\n          \"indexed\": false,\n          \"name\": \"accessCharge\",\n          \"type\": \"uint256\"\n        },\n        {\n          \"indexed\": false,\n          \"name\": \"amountProvided\",\n          \"type\": \"uint256\"\n        }\n      ],\n      \"name\": \"InsufficientFunds\",\n      \"type\": \"event\"\n    },\n    {\n      \"anonymous\": false,\n      \"inputs\": [\n        {\n          \"indexed\": false,\n          \"name\": \"statusCode\",\n          \"type\": \"int256\"\n        }\n      ],\n      \"name\": \"SetStatusCode\",\n      \"type\": \"event\"\n    },\n    {\n      \"anonymous\": false,\n      \"inputs\": [\n        {\n          \"indexed\": false,\n          \"name\": \"requestStatus\",\n          \"type\": \"bool\"\n        },\n        {\n          \"indexed\": false,\n          \"name\": \"statusCode\",\n          \"type\": \"int256\"\n        },\n        {\n          \"indexed\": false,\n          \"name\": \"objectHash\",\n          \"type\": \"bytes32\"\n        }\n      ],\n      \"name\": \"Publish\",\n      \"type\": \"event\"\n    },\n    {\n      \"anonymous\": false,\n      \"inputs\": [\n        {\n          \"indexed\": false,\n          \"name\": \"custom_contract\",\n          \"type\": \"address\"\n        }\n      ],\n      \"name\": \"InvokeCustomPreHook\",\n      \"type\": \"event\"\n    },\n    {\n      \"anonymous\": false,\n      \"inputs\": [\n        {\n          \"indexed\": false,\n          \"name\": \"custom_contract\",\n          \"type\": \"address\"\n        },\n        {\n          \"indexed\": false,\n          \"name\": \"result\",\n          \"type\": \"uint256\"\n        }\n      ],\n      \"name\": \"ReturnCustomHook\",\n      \"type\": \"event\"\n    },\n    {\n      \"anonymous\": false,\n      \"inputs\": [\n        {\n          \"indexed\": false,\n          \"name\": \"custom_contract\",\n          \"type\": \"address\"\n        }\n      ],\n      \"name\": \"InvokeCustomPostHook\",\n      \"type\": \"event\"\n    },\n    {\n      \"anonymous\": false,\n      \"inputs\": [\n        {\n          \"indexed\": false,\n          \"name\": \"objectHash\",\n          \"type\": \"bytes32\"\n        }\n      ],\n      \"name\": \"CommitPending\",\n      \"type\": \"event\"\n    },\n    {\n      \"anonymous\": false,\n      \"inputs\": [\n        {\n          \"indexed\": false,\n          \"name\": \"objectHash\",\n          \"type\": \"bytes32\"\n        }\n      ],\n      \"name\": \"Commit\",\n      \"type\": \"event\"\n    },\n    {\n      \"anonymous\": false,\n      \"inputs\": [\n        {\n          \"indexed\": false,\n          \"name\": \"objectHash\",\n          \"type\": \"bytes32\"\n        }\n      ],\n      \"name\": \"UpdateRequest\",\n      \"type\": \"event\"\n    }\n  ],\n  \"event\": {\n    \"to\": \"0x61E76Bc8b01352A2b12d8e8949F9c1CDF6ca447D\",\n    \"from\": \"0xc2635Ab30Fc19F616332c6d2d7F14cdAf7ce1965\",\n    \"contractAddress\": null,\n    \"transactionIndex\": 0,\n    \"gasUsed\": {\n      \"_hex\": \"0x153de\"\n    },\n    \"logsBloom\": \"0x00000000000000000000000000040000000000000000000000000000000000000000000000000000000000000000000000000000000000000000000000000000080000000000000004000000000000000000000000000000000000000000000000400000000000000000000000000000000000000000000000000000000000000000000000000000000000000000000000000000000000000001000000000000000000000000000000000000000000000000000000000000000000000000000000000000000000000000000000000000000000000000000000000000000000000000000000000000000000000000000000000000000000000000002000000000\",\n    \"blockHash\": \"0xde5ed653eeb38163045a585228717f4435e17ad2d1db8fe3eaa4e498e356f0e6\",\n    \"transactionHash\": \"0x9a79d749e9aea805fb0ec9431678abe7f13d91f6f1f4e7dac53b096f416bfddd\",\n    \"logs\": [\n      {\n        \"transactionIndex\": 0,\n        \"blockNumber\": 761,\n        \"transactionHash\": \"0x9a79d749e9aea805fb0ec9431678abe7f13d91f6f1f4e7dac53b096f416bfddd\",\n        \"address\": \"0x61E76Bc8b01352A2b12d8e8949F9c1CDF6ca447D\",\n        \"topics\": [\n          \"0x089a6f1788a3c353423e1be4ba12533bdde7d908bb41abeee185af0acb3df562\"\n        ],\n        \"data\": \"0x00000000000000000000000000000000000000000000000000000000000000030000000000000000000000000000000000000000000000000000000000000000000000000000000000000000000000000000000000000000000000000000000000000000000000000000000000000000000000000000000000000000000000a000000000000000000000000000000000000000000000000000000000000001600000000000000000000000000000000000000000000000000000000000000084307830346662626561336262633038303466303565383233643233313232383538666137323164663765396331363939336238316362373761323961373236393361303733626562633030383730343737323036626531623830383037306162316162666231366365616264613963623535643633623332653734396230623162633033000000000000000000000000000000000000000000000000000000000000000000000000000000000000000000000000000000000000000000000000\",\n        \"logIndex\": 0,\n        \"blockHash\": \"0xde5ed653eeb38163045a585228717f4435e17ad2d1db8fe3eaa4e498e356f0e6\",\n        \"transactionLogIndex\": 0,\n        \"name\": \"AccessRequest\",\n        \"signature\": \"AccessRequest(uint256,uint8,bytes32,string,string)\",\n        \"topic\": \"0x089a6f1788a3c353423e1be4ba12533bdde7d908bb41abeee185af0acb3df562\",\n        \"values\": {\n          \"0\": {\n            \"_hex\": \"0x03\"\n          },\n          \"1\": 0,\n          \"2\": \"0x0000000000000000000000000000000000000000000000000000000000000000\",\n          \"3\": \"0x04fbbea3bbc0804f05e823d23122858fa721df7e9c16993b81cb77a29a72693a073bebc00870477206be1b808070ab1abfb16ceabda9cb55d63b32e749b0b1bc03\",\n          \"4\": \"\",\n          \"requestID\": {\n            \"_hex\": \"0x03\"\n          },\n          \"level\": 0,\n          \"contentHash\": \"0x0000000000000000000000000000000000000000000000000000000000000000\",\n          \"pkeRequestor\": \"0x04fbbea3bbc0804f05e823d23122858fa721df7e9c16993b81cb77a29a72693a073bebc00870477206be1b808070ab1abfb16ceabda9cb55d63b32e749b0b1bc03\",\n          \"pkeAFGH\": \"\",\n          \"length\": 5\n        }\n      }\n    ],\n    \"blockNumber\": 761,\n    \"confirmations\": 1,\n    \"cumulativeGasUsed\": {\n      \"_hex\": \"0x153de\"\n    },\n    \"status\": 1,\n    \"byzantium\": true\n  },\n  \"eventName\": \"AccessRequest\"\n});",
    "result": "{\n  \"name\": \"AccessRequest\",\n  \"signature\": \"AccessRequest(uint256,uint8,bytes32,string,string)\",\n  \"topic\": \"0x089a6f1788a3c353423e1be4ba12533bdde7d908bb41abeee185af0acb3df562\",\n  \"values\": {\n    \"0\": {\n      \"_hex\": \"0x03\"\n    },\n    \"1\": 0,\n    \"2\": \"0x0000000000000000000000000000000000000000000000000000000000000000\",\n    \"3\": \"0x04fbbea3bbc0804f05e823d23122858fa721df7e9c16993b81cb77a29a72693a073bebc00870477206be1b808070ab1abfb16ceabda9cb55d63b32e749b0b1bc03\",\n    \"4\": \"\",\n    \"requestID\": {\n      \"_hex\": \"0x03\"\n    },\n    \"level\": 0,\n    \"contentHash\": \"0x0000000000000000000000000000000000000000000000000000000000000000\",\n    \"pkeRequestor\": \"0x04fbbea3bbc0804f05e823d23122858fa721df7e9c16993b81cb77a29a72693a073bebc00870477206be1b808070ab1abfb16ceabda9cb55d63b32e749b0b1bc03\",\n    \"pkeAFGH\": \"\",\n    \"length\": 5\n  }\n}"
  }
]